{"v":"5.1.13","fr":60,"ip":0,"op":120,"w":512,"h":512,"nm":"Comp 1","ddd":0,"assets":[],"layers":[{"ddd":0,"ind":1,"ty":4,"nm":"walletAnimate Outlines","sr":1,"ks":{"o":{"a":0,"k":100,"ix":11},"r":{"a":0,"k":0,"ix":10},"p":{"a":0,"k":[256,256,0],"ix":2},"a":{"a":0,"k":[256,256,0],"ix":1},"s":{"a":0,"k":[100,100,100],"ix":6}},"ao":0,"shapes":[{"ty":"gr","it":[{"ty":"gr","it":[{"ind":0,"ty":"sh","ix":1,"ks":{"a":0,"k":{"i":[[0,0],[0,0],[0,0],[0,0],[0,0],[0,0],[0,0],[0,0],[0,0]],"o":[[0,0],[0,0],[0,0],[0,0],[0,0],[0,0],[0,0],[0,0],[0,0]],"v":[[-5.239,27.15],[5.239,27.15],[5.239,-2.788],[24.035,16.008],[31.426,8.616],[0,-22.81],[-31.426,8.616],[-24.035,16.008],[-5.239,-2.788]],"c":true},"ix":2},"nm":"Path 1","mn":"ADBE Vector Shape - Group","hd":false},{"ind":1,"ty":"sh","ix":2,"ks":{"a":0,"k":{"i":[[0,0],[0,0],[0,0],[0,0],[0,0],[0,0],[0,0],[0,0],[0,0]],"o":[[0,0],[0,0],[0,0],[0,0],[0,0],[0,0],[0,0],[0,0],[0,0]],"v":[[15.718,37.629],[-15.718,37.629],[-15.718,22.509],[-24.035,30.827],[-46.244,8.616],[0,-37.629],[46.244,8.616],[24.035,30.827],[15.718,22.509]],"c":true},"ix":2},"nm":"Path 2","mn":"ADBE Vector Shape - Group","hd":false},{"ty":"mm","mm":1,"nm":"Merge Paths 1","mn":"ADBE Vector Filter - Merge","hd":false},{"ty":"fl","c":{"a":0,"k":[0,0,0,1],"ix":4},"o":{"a":0,"k":100,"ix":5},"r":1,"nm":"Fill 1","mn":"ADBE Vector Graphic - Fill","hd":false},{"ty":"tr","p":{"a":0,"k":[159.538,151.216],"ix":2},"a":{"a":0,"k":[0,0],"ix":1},"s":{"a":0,"k":[100,100],"ix":3},"r":{"a":0,"k":0,"ix":6},"o":{"a":0,"k":100,"ix":7},"sk":{"a":0,"k":0,"ix":4},"sa":{"a":0,"k":0,"ix":5},"nm":"Transform"}],"nm":"Group 10","np":4,"cix":2,"ix":1,"mn":"ADBE Vector Group","hd":false},{"ty":"gr","it":[{"ind":0,"ty":"sh","ix":1,"ks":{"a":0,"k":{"i":[[0,0],[0,0],[0,0],[0,0],[0,0],[0,0],[0,0],[0,0],[0,0]],"o":[[0,0],[0,0],[0,0],[0,0],[0,0],[0,0],[0,0],[0,0],[0,0]],"v":[[38.835,7.531],[0,-31.303],[-38.836,7.531],[-24.035,22.333],[-10.479,8.776],[-10.479,31.303],[10.478,31.303],[10.478,8.776],[24.034,22.333]],"c":true},"ix":2},"nm":"Path 1","mn":"ADBE Vector Shape - Group","hd":false},{"ty":"fl","c":{"a":0,"k":[1,1,1,1],"ix":4},"o":{"a":0,"k":100,"ix":5},"r":1,"nm":"Fill 1","mn":"ADBE Vector Graphic - Fill","hd":false},{"ty":"tr","p":{"a":0,"k":[159.538,152.302],"ix":2},"a":{"a":0,"k":[0,0],"ix":1},"s":{"a":0,"k":[100,100],"ix":3},"r":{"a":0,"k":0,"ix":6},"o":{"a":0,"k":100,"ix":7},"sk":{"a":0,"k":0,"ix":4},"sa":{"a":0,"k":0,"ix":5},"nm":"Transform"}],"nm":"Group 11","np":2,"cix":2,"ix":2,"mn":"ADBE Vector Group","hd":false},{"ty":"gr","it":[{"ind":0,"ty":"sh","ix":1,"ks":{"a":0,"k":{"i":[[0,0],[0,0],[0,0],[0,0],[0,0],[0,0],[0,0],[0,0],[0,0],[0,0],[0,0],[0,0]],"o":[[0,0],[0,0],[0,0],[0,0],[0,0],[0,0],[0,0],[0,0],[0,0],[0,0],[0,0],[0,0]],"v":[[-5.24,31.434],[5.239,31.434],[5.239,5.239],[31.435,5.239],[31.435,-5.239],[5.239,-5.239],[5.239,-31.436],[-5.24,-31.436],[-5.24,-5.239],[-31.435,-5.239],[-31.435,5.239],[-5.24,5.239]],"c":true},"ix":2},"nm":"Path 1","mn":"ADBE Vector Shape - Group","hd":false},{"ind":1,"ty":"sh","ix":2,"ks":{"a":0,"k":{"i":[[0,0],[0,0],[0,0],[0,0],[0,0],[0,0],[0,0],[0,0],[0,0],[0,0],[0,0],[0,0]],"o":[[0,0],[0,0],[0,0],[0,0],[0,0],[0,0],[0,0],[0,0],[0,0],[0,0],[0,0],[0,0]],"v":[[15.717,41.913],[-15.719,41.913],[-15.719,15.718],[-41.914,15.718],[-41.914,-15.717],[-15.719,-15.717],[-15.719,-41.913],[15.717,-41.913],[15.717,-15.717],[41.913,-15.717],[41.913,15.718],[15.717,15.718]],"c":true},"ix":2},"nm":"Path 2","mn":"ADBE Vector Shape - Group","hd":false},{"ty":"mm","mm":1,"nm":"Merge Paths 1","mn":"ADBE Vector Filter - Merge","hd":false},{"ty":"fl","c":{"a":0,"k":[0,0,0,1],"ix":4},"o":{"a":0,"k":100,"ix":5},"r":1,"nm":"Fill 1","mn":"ADBE Vector Graphic - Fill","hd":false},{"ty":"tr","p":{"a":0,"k":[356.793,157.41],"ix":2},"a":{"a":0,"k":[0,0],"ix":1},"s":{"a":0,"k":[100,100],"ix":3},"r":{"a":0,"k":0,"ix":6},"o":{"a":0,"k":100,"ix":7},"sk":{"a":0,"k":0,"ix":4},"sa":{"a":0,"k":0,"ix":5},"nm":"Transform"}],"nm":"Group 12","np":4,"cix":2,"ix":3,"mn":"ADBE Vector Group","hd":false},{"ty":"gr","it":[{"ind":0,"ty":"sh","ix":1,"ks":{"a":0,"k":{"i":[[0,0],[0,0],[0,0],[0,0],[0,0],[0,0],[0,0],[0,0],[0,0],[0,0],[0,0],[0,0]],"o":[[0,0],[0,0],[0,0],[0,0],[0,0],[0,0],[0,0],[0,0],[0,0],[0,0],[0,0],[0,0]],"v":[[10.479,-10.478],[10.479,-36.674],[-10.478,-36.674],[-10.478,-10.478],[-36.673,-10.478],[-36.673,10.479],[-10.478,10.479],[-10.478,36.674],[10.479,36.674],[10.479,10.479],[36.673,10.479],[36.673,-10.478]],"c":true},"ix":2},"nm":"Path 1","mn":"ADBE Vector Shape - Group","hd":false},{"ty":"fl","c":{"a":0,"k":[1,1,1,1],"ix":4},"o":{"a":0,"k":100,"ix":5},"r":1,"nm":"Fill 1","mn":"ADBE Vector Graphic - Fill","hd":false},{"ty":"tr","p":{"a":0,"k":[356.793,157.41],"ix":2},"a":{"a":0,"k":[0,0],"ix":1},"s":{"a":0,"k":[100,100],"ix":3},"r":{"a":0,"k":0,"ix":6},"o":{"a":0,"k":100,"ix":7},"sk":{"a":0,"k":0,"ix":4},"sa":{"a":0,"k":0,"ix":5},"nm":"Transform"}],"nm":"Group 13","np":2,"cix":2,"ix":4,"mn":"ADBE Vector Group","hd":false},{"ty":"gr","it":[{"ind":0,"ty":"sh","ix":1,"ks":{"a":0,"k":{"i":[[11.526,0],[0,-11.526],[-11.526,0],[0,11.526]],"o":[[-11.526,0],[0,11.526],[11.526,0],[0,-11.526]],"v":[[0,-20.957],[-20.957,0],[0,20.957],[20.957,0]],"c":true},"ix":2},"nm":"Path 1","mn":"ADBE Vector Shape - Group","hd":false},{"ind":1,"ty":"sh","ix":2,"ks":{"a":0,"k":{"i":[[-5.763,0],[0,-5.763],[5.763,0],[0,5.764]],"o":[[5.763,0],[0,5.764],[-5.763,0],[0,-5.828]],"v":[[0,-10.478],[10.478,0],[0,10.479],[-10.479,0]],"c":true},"ix":2},"nm":"Path 2","mn":"ADBE Vector Shape - Group","hd":false},{"ty":"mm","mm":1,"nm":"Merge Paths 1","mn":"ADBE Vector Filter - Merge","hd":false},{"ty":"fl","c":{"a":0,"k":[0,0,0,1],"ix":4},"o":{"a":0,"k":100,"ix":5},"r":1,"nm":"Fill 1","mn":"ADBE Vector Graphic - Fill","hd":false},{"ty":"tr","p":{"a":0,"k":[251.878,325.195],"ix":2},"a":{"a":0,"k":[0,0],"ix":1},"s":{"a":0,"k":[100,100],"ix":3},"r":{"a":0,"k":0,"ix":6},"o":{"a":0,"k":100,"ix":7},"sk":{"a":0,"k":0,"ix":4},"sa":{"a":0,"k":0,"ix":5},"nm":"Transform"}],"nm":"Group 14","np":4,"cix":2,"ix":5,"mn":"ADBE Vector Group","hd":false},{"ty":"gr","it":[{"ind":0,"ty":"sh","ix":1,"ks":{"a":0,"k":{"i":[[8.645,0],[0,8.645],[-8.645,0],[0,-8.644]],"o":[[-8.645,0],[0,-8.644],[8.645,0],[0,8.645]],"v":[[0,15.718],[-15.717,0],[0,-15.718],[15.717,0]],"c":true},"ix":2},"nm":"Path 1","mn":"ADBE Vector Shape - Group","hd":false},{"ty":"fl","c":{"a":0,"k":[0.481999984442,0.819999964097,0.33300000359,1],"ix":4},"o":{"a":0,"k":100,"ix":5},"r":1,"nm":"Fill 1","mn":"ADBE Vector Graphic - Fill","hd":false},{"ty":"tr","p":{"a":0,"k":[251.878,325.194],"ix":2},"a":{"a":0,"k":[0,0],"ix":1},"s":{"a":0,"k":[100,100],"ix":3},"r":{"a":0,"k":0,"ix":6},"o":{"a":0,"k":100,"ix":7},"sk":{"a":0,"k":0,"ix":4},"sa":{"a":0,"k":0,"ix":5},"nm":"Transform"}],"nm":"Group 15","np":2,"cix":2,"ix":6,"mn":"ADBE Vector Group","hd":false},{"ty":"gr","it":[{"ind":0,"ty":"sh","ix":1,"ks":{"a":0,"k":{"i":[[0,0],[0,0],[0,0],[0,0]],"o":[[0,0],[0,0],[0,0],[0,0]],"v":[[-120.501,5.24],[-130.98,5.24],[-130.98,-5.24],[-120.501,-5.24]],"c":true},"ix":2},"nm":"Path 1","mn":"ADBE Vector Shape - Group","hd":false},{"ind":1,"ty":"sh","ix":2,"ks":{"a":0,"k":{"i":[[0,0],[0,0],[0,0],[0,0]],"o":[[0,0],[0,0],[0,0],[0,0]],"v":[[-99.544,5.24],[-110.023,5.24],[-110.023,-5.24],[-99.544,-5.24]],"c":true},"ix":2},"nm":"Path 2","mn":"ADBE Vector Shape - Group","hd":false},{"ind":2,"ty":"sh","ix":3,"ks":{"a":0,"k":{"i":[[0,0],[0,0],[0,0],[0,0]],"o":[[0,0],[0,0],[0,0],[0,0]],"v":[[-78.587,5.24],[-89.064,5.24],[-89.064,-5.24],[-78.587,-5.24]],"c":true},"ix":2},"nm":"Path 3","mn":"ADBE Vector Shape - Group","hd":false},{"ind":3,"ty":"sh","ix":4,"ks":{"a":0,"k":{"i":[[0,0],[0,0],[0,0],[0,0]],"o":[[0,0],[0,0],[0,0],[0,0]],"v":[[-57.63,5.24],[-68.109,5.24],[-68.109,-5.24],[-57.63,-5.24]],"c":true},"ix":2},"nm":"Path 4","mn":"ADBE Vector Shape - Group","hd":false},{"ind":4,"ty":"sh","ix":5,"ks":{"a":0,"k":{"i":[[0,0],[0,0],[0,0],[0,0]],"o":[[0,0],[0,0],[0,0],[0,0]],"v":[[-36.674,5.24],[-47.153,5.24],[-47.153,-5.24],[-36.674,-5.24]],"c":true},"ix":2},"nm":"Path 5","mn":"ADBE Vector Shape - Group","hd":false},{"ind":5,"ty":"sh","ix":6,"ks":{"a":0,"k":{"i":[[0,0],[0,0],[0,0],[0,0]],"o":[[0,0],[0,0],[0,0],[0,0]],"v":[[-15.717,5.24],[-26.196,5.24],[-26.196,-5.24],[-15.717,-5.24]],"c":true},"ix":2},"nm":"Path 6","mn":"ADBE Vector Shape - Group","hd":false},{"ind":6,"ty":"sh","ix":7,"ks":{"a":0,"k":{"i":[[0,0],[0,0],[0,0],[0,0]],"o":[[0,0],[0,0],[0,0],[0,0]],"v":[[5.24,5.24],[-5.238,5.24],[-5.238,-5.24],[5.24,-5.24]],"c":true},"ix":2},"nm":"Path 7","mn":"ADBE Vector Shape - Group","hd":false},{"ind":7,"ty":"sh","ix":8,"ks":{"a":0,"k":{"i":[[0,0],[0,0],[0,0],[0,0]],"o":[[0,0],[0,0],[0,0],[0,0]],"v":[[26.197,5.24],[15.717,5.24],[15.717,-5.24],[26.197,-5.24]],"c":true},"ix":2},"nm":"Path 8","mn":"ADBE Vector Shape - Group","hd":false},{"ind":8,"ty":"sh","ix":9,"ks":{"a":0,"k":{"i":[[0,0],[0,0],[0,0],[0,0]],"o":[[0,0],[0,0],[0,0],[0,0]],"v":[[47.154,5.24],[36.674,5.24],[36.674,-5.24],[47.154,-5.24]],"c":true},"ix":2},"nm":"Path 9","mn":"ADBE Vector Shape - Group","hd":false},{"ind":9,"ty":"sh","ix":10,"ks":{"a":0,"k":{"i":[[0,0],[0,0],[0,0],[0,0]],"o":[[0,0],[0,0],[0,0],[0,0]],"v":[[68.109,5.24],[57.632,5.24],[57.632,-5.24],[68.109,-5.24]],"c":true},"ix":2},"nm":"Path 10","mn":"ADBE Vector Shape - Group","hd":false},{"ind":10,"ty":"sh","ix":11,"ks":{"a":0,"k":{"i":[[0,0],[0,0],[0,0],[0,0]],"o":[[0,0],[0,0],[0,0],[0,0]],"v":[[89.066,5.24],[78.587,5.24],[78.587,-5.24],[89.066,-5.24]],"c":true},"ix":2},"nm":"Path 11","mn":"ADBE Vector Shape - Group","hd":false},{"ind":11,"ty":"sh","ix":12,"ks":{"a":0,"k":{"i":[[0,0],[0,0],[0,0],[0,0]],"o":[[0,0],[0,0],[0,0],[0,0]],"v":[[110.023,5.24],[99.544,5.24],[99.544,-5.24],[110.023,-5.24]],"c":true},"ix":2},"nm":"Path 12","mn":"ADBE Vector Shape - Group","hd":false},{"ind":12,"ty":"sh","ix":13,"ks":{"a":0,"k":{"i":[[0,0],[0,0],[0,0],[0,0]],"o":[[0,0],[0,0],[0,0],[0,0]],"v":[[130.979,5.24],[120.501,5.24],[120.501,-5.24],[130.979,-5.24]],"c":true},"ix":2},"nm":"Path 13","mn":"ADBE Vector Shape - Group","hd":false},{"ty":"mm","mm":1,"nm":"Merge Paths 1","mn":"ADBE Vector Filter - Merge","hd":false},{"ty":"fl","c":{"a":0,"k":[0,0,0,1],"ix":4},"o":{"a":0,"k":100,"ix":5},"r":1,"nm":"Fill 1","mn":"ADBE Vector Graphic - Fill","hd":false},{"ty":"tr","p":{"a":0,"k":[251.878,361.083],"ix":2},"a":{"a":0,"k":[0,0],"ix":1},"s":{"a":0,"k":[100,100],"ix":3},"r":{"a":0,"k":0,"ix":6},"o":{"a":0,"k":100,"ix":7},"sk":{"a":0,"k":0,"ix":4},"sa":{"a":0,"k":0,"ix":5},"nm":"Transform"}],"nm":"Group 16","np":15,"cix":2,"ix":7,"mn":"ADBE Vector Group","hd":false},{"ty":"gr","it":[{"ind":0,"ty":"sh","ix":1,"ks":{"a":0,"k":{"i":[[0,0],[0,0],[0,0],[0,0]],"o":[[0,0],[0,0],[0,0],[0,0]],"v":[[-120.501,5.24],[-130.98,5.24],[-130.98,-5.24],[-120.501,-5.24]],"c":true},"ix":2},"nm":"Path 1","mn":"ADBE Vector Shape - Group","hd":false},{"ind":1,"ty":"sh","ix":2,"ks":{"a":0,"k":{"i":[[0,0],[0,0],[0,0],[0,0]],"o":[[0,0],[0,0],[0,0],[0,0]],"v":[[-99.544,5.24],[-110.023,5.24],[-110.023,-5.24],[-99.544,-5.24]],"c":true},"ix":2},"nm":"Path 2","mn":"ADBE Vector Shape - Group","hd":false},{"ind":2,"ty":"sh","ix":3,"ks":{"a":0,"k":{"i":[[0,0],[0,0],[0,0],[0,0]],"o":[[0,0],[0,0],[0,0],[0,0]],"v":[[-78.587,5.24],[-89.064,5.24],[-89.064,-5.24],[-78.587,-5.24]],"c":true},"ix":2},"nm":"Path 3","mn":"ADBE Vector Shape - Group","hd":false},{"ind":3,"ty":"sh","ix":4,"ks":{"a":0,"k":{"i":[[0,0],[0,0],[0,0],[0,0]],"o":[[0,0],[0,0],[0,0],[0,0]],"v":[[-57.63,5.24],[-68.109,5.24],[-68.109,-5.24],[-57.63,-5.24]],"c":true},"ix":2},"nm":"Path 4","mn":"ADBE Vector Shape - Group","hd":false},{"ind":4,"ty":"sh","ix":5,"ks":{"a":0,"k":{"i":[[0,0],[0,0],[0,0],[0,0]],"o":[[0,0],[0,0],[0,0],[0,0]],"v":[[-36.674,5.24],[-47.153,5.24],[-47.153,-5.24],[-36.674,-5.24]],"c":true},"ix":2},"nm":"Path 5","mn":"ADBE Vector Shape - Group","hd":false},{"ind":5,"ty":"sh","ix":6,"ks":{"a":0,"k":{"i":[[0,0],[0,0],[0,0],[0,0]],"o":[[0,0],[0,0],[0,0],[0,0]],"v":[[-15.717,5.24],[-26.196,5.24],[-26.196,-5.24],[-15.717,-5.24]],"c":true},"ix":2},"nm":"Path 6","mn":"ADBE Vector Shape - Group","hd":false},{"ind":6,"ty":"sh","ix":7,"ks":{"a":0,"k":{"i":[[0,0],[0,0],[0,0],[0,0]],"o":[[0,0],[0,0],[0,0],[0,0]],"v":[[5.24,5.24],[-5.238,5.24],[-5.238,-5.24],[5.24,-5.24]],"c":true},"ix":2},"nm":"Path 7","mn":"ADBE Vector Shape - Group","hd":false},{"ind":7,"ty":"sh","ix":8,"ks":{"a":0,"k":{"i":[[0,0],[0,0],[0,0],[0,0]],"o":[[0,0],[0,0],[0,0],[0,0]],"v":[[26.197,5.24],[15.717,5.24],[15.717,-5.24],[26.197,-5.24]],"c":true},"ix":2},"nm":"Path 8","mn":"ADBE Vector Shape - Group","hd":false},{"ind":8,"ty":"sh","ix":9,"ks":{"a":0,"k":{"i":[[0,0],[0,0],[0,0],[0,0]],"o":[[0,0],[0,0],[0,0],[0,0]],"v":[[47.154,5.24],[36.674,5.24],[36.674,-5.24],[47.154,-5.24]],"c":true},"ix":2},"nm":"Path 9","mn":"ADBE Vector Shape - Group","hd":false},{"ind":9,"ty":"sh","ix":10,"ks":{"a":0,"k":{"i":[[0,0],[0,0],[0,0],[0,0]],"o":[[0,0],[0,0],[0,0],[0,0]],"v":[[68.109,5.24],[57.632,5.24],[57.632,-5.24],[68.109,-5.24]],"c":true},"ix":2},"nm":"Path 10","mn":"ADBE Vector Shape - Group","hd":false},{"ind":10,"ty":"sh","ix":11,"ks":{"a":0,"k":{"i":[[0,0],[0,0],[0,0],[0,0]],"o":[[0,0],[0,0],[0,0],[0,0]],"v":[[89.066,5.24],[78.587,5.24],[78.587,-5.24],[89.066,-5.24]],"c":true},"ix":2},"nm":"Path 11","mn":"ADBE Vector Shape - Group","hd":false},{"ind":11,"ty":"sh","ix":12,"ks":{"a":0,"k":{"i":[[0,0],[0,0],[0,0],[0,0]],"o":[[0,0],[0,0],[0,0],[0,0]],"v":[[110.023,5.24],[99.544,5.24],[99.544,-5.24],[110.023,-5.24]],"c":true},"ix":2},"nm":"Path 12","mn":"ADBE Vector Shape - Group","hd":false},{"ind":12,"ty":"sh","ix":13,"ks":{"a":0,"k":{"i":[[0,0],[0,0],[0,0],[0,0]],"o":[[0,0],[0,0],[0,0],[0,0]],"v":[[130.979,5.24],[120.501,5.24],[120.501,-5.24],[130.979,-5.24]],"c":true},"ix":2},"nm":"Path 13","mn":"ADBE Vector Shape - Group","hd":false},{"ty":"mm","mm":1,"nm":"Merge Paths 1","mn":"ADBE Vector Filter - Merge","hd":false},{"ty":"fl","c":{"a":0,"k":[0,0,0,1],"ix":4},"o":{"a":0,"k":100,"ix":5},"r":1,"nm":"Fill 1","mn":"ADBE Vector Graphic - Fill","hd":false},{"ty":"tr","p":{"a":0,"k":[251.878,288.389],"ix":2},"a":{"a":0,"k":[0,0],"ix":1},"s":{"a":0,"k":[100,100],"ix":3},"r":{"a":0,"k":0,"ix":6},"o":{"a":0,"k":100,"ix":7},"sk":{"a":0,"k":0,"ix":4},"sa":{"a":0,"k":0,"ix":5},"nm":"Transform"}],"nm":"Group 17","np":15,"cix":2,"ix":8,"mn":"ADBE Vector Group","hd":false},{"ty":"gr","it":[{"ind":0,"ty":"sh","ix":1,"ks":{"a":0,"k":{"i":[[0,0],[0,-8.667],[0,0],[-8.667,0],[0,0],[0,8.667],[0,0],[5.892,0]],"o":[[-8.667,0],[0,0],[0,8.667],[0,0],[8.666,0],[0,0],[-4.381,3.296],[0,0]],"v":[[-115.262,-55.011],[-130.979,-39.293],[-130.979,55.01],[-115.262,70.729],[115.262,70.729],[130.979,55.01],[130.979,-60.263],[115.262,-55.011]],"c":true},"ix":2},"nm":"Path 1","mn":"ADBE Vector Shape - Group","hd":false},{"ind":1,"ty":"sh","ix":2,"ks":{"a":0,"k":{"i":[[14.445,0],[0,0],[0,14.445],[0,0],[-14.444,0],[0,0],[0,8.667],[0,0],[0,0]],"o":[[0,0],[-14.444,0],[0,0],[0,-14.445],[0,0],[8.666,0],[0,0],[0,0],[0,14.445]],"v":[[115.262,81.208],[-115.262,81.208],[-141.458,55.01],[-141.458,-39.293],[-115.262,-65.49],[115.262,-65.49],[130.979,-81.207],[141.458,-81.207],[141.458,55.01]],"c":true},"ix":2},"nm":"Path 2","mn":"ADBE Vector Shape - Group","hd":false},{"ty":"mm","mm":1,"nm":"Merge Paths 1","mn":"ADBE Vector Filter - Merge","hd":false},{"ty":"fl","c":{"a":0,"k":[0,0,0,1],"ix":4},"o":{"a":0,"k":100,"ix":5},"r":1,"nm":"Fill 1","mn":"ADBE Vector Graphic - Fill","hd":false},{"ty":"tr","p":{"a":0,"k":[257.117,317.205],"ix":2},"a":{"a":0,"k":[0,0],"ix":1},"s":{"a":0,"k":[100,100],"ix":3},"r":{"a":0,"k":0,"ix":6},"o":{"a":0,"k":100,"ix":7},"sk":{"a":0,"k":0,"ix":4},"sa":{"a":0,"k":0,"ix":5},"nm":"Transform"}],"nm":"Group 18","np":4,"cix":2,"ix":9,"mn":"ADBE Vector Group","hd":false},{"ty":"gr","it":[{"ind":0,"ty":"sh","ix":1,"ks":{"a":0,"k":{"i":[[11.592,0],[0,0],[0,0],[0,-11.592],[0,0],[-11.592,0],[0,0],[0,0],[0,11.592],[0,0]],"o":[[0,0],[0,0],[-11.592,0],[0,0],[0,11.592],[0,0],[0,0],[11.592,0],[0,0],[0,11.592]],"v":[[115.263,-57.631],[94.306,-57.631],[-115.261,-57.631],[-136.218,-36.674],[-136.218,57.631],[-115.261,78.588],[94.306,78.588],[115.263,78.588],[136.219,57.631],[136.219,-78.588]],"c":true},"ix":2},"nm":"Path 1","mn":"ADBE Vector Shape - Group","hd":false},{"ty":"fl","c":{"a":0,"k":[0.536999990426,0.458999992819,0,1],"ix":4},"o":{"a":0,"k":100,"ix":5},"r":1,"nm":"Fill 1","mn":"ADBE Vector Graphic - Fill","hd":false},{"ty":"tr","p":{"a":0,"k":[257.117,314.585],"ix":2},"a":{"a":0,"k":[0,0],"ix":1},"s":{"a":0,"k":[100,100],"ix":3},"r":{"a":0,"k":0,"ix":6},"o":{"a":0,"k":100,"ix":7},"sk":{"a":0,"k":0,"ix":4},"sa":{"a":0,"k":0,"ix":5},"nm":"Transform"}],"nm":"Group 19","np":2,"cix":2,"ix":10,"mn":"ADBE Vector Group","hd":false},{"ty":"gr","it":[{"ind":0,"ty":"sh","ix":1,"ks":{"a":0,"k":{"i":[[0,0],[0,0],[0,0],[0,0]],"o":[[0,0],[0,0],[0,0],[0,0]],"v":[[33.489,-29.785],[29.784,-33.489],[39.047,-42.751],[42.751,-39.047]],"c":true},"ix":2},"nm":"Path 1","mn":"ADBE Vector Shape - Group","hd":false},{"ind":1,"ty":"sh","ix":2,"ks":{"a":0,"k":{"i":[[0,0],[0,0],[0,0],[0,0]],"o":[[0,0],[0,0],[0,0],[0,0]],"v":[[20.522,-16.818],[16.818,-20.522],[26.079,-29.785],[29.784,-26.08]],"c":true},"ix":2},"nm":"Path 2","mn":"ADBE Vector Shape - Group","hd":false},{"ind":2,"ty":"sh","ix":3,"ks":{"a":0,"k":{"i":[[0,0],[0,0],[0,0],[0,0]],"o":[[0,0],[0,0],[0,0],[0,0]],"v":[[7.556,-3.852],[3.852,-7.556],[13.114,-16.818],[16.818,-13.114]],"c":true},"ix":2},"nm":"Path 3","mn":"ADBE Vector Shape - Group","hd":false},{"ind":3,"ty":"sh","ix":4,"ks":{"a":0,"k":{"i":[[0,0],[0,0],[0,0],[0,0]],"o":[[0,0],[0,0],[0,0],[0,0]],"v":[[-5.41,9.114],[-9.115,5.409],[0.147,-3.852],[3.852,-0.148]],"c":true},"ix":2},"nm":"Path 4","mn":"ADBE Vector Shape - Group","hd":false},{"ind":4,"ty":"sh","ix":5,"ks":{"a":0,"k":{"i":[[0,0],[0,0],[0,0],[0,0]],"o":[[0,0],[0,0],[0,0],[0,0]],"v":[[-18.376,22.08],[-22.08,18.376],[-12.82,9.114],[-9.115,12.819]],"c":true},"ix":2},"nm":"Path 5","mn":"ADBE Vector Shape - Group","hd":false},{"ind":5,"ty":"sh","ix":6,"ks":{"a":0,"k":{"i":[[0,0],[0,0],[0,0],[0,0]],"o":[[0,0],[0,0],[0,0],[0,0]],"v":[[-31.342,35.046],[-35.047,31.342],[-25.785,22.081],[-22.081,25.785]],"c":true},"ix":2},"nm":"Path 6","mn":"ADBE Vector Shape - Group","hd":false},{"ind":6,"ty":"sh","ix":7,"ks":{"a":0,"k":{"i":[[0,0],[0,0],[0,0],[0,0]],"o":[[0,0],[0,0],[0,0],[0,0]],"v":[[-39.046,42.75],[-42.75,39.046],[-38.751,35.047],[-35.047,38.751]],"c":true},"ix":2},"nm":"Path 7","mn":"ADBE Vector Shape - Group","hd":false},{"ty":"mm","mm":1,"nm":"Merge Paths 1","mn":"ADBE Vector Filter - Merge","hd":false},{"ty":"fl","c":{"a":0,"k":[0,0,0,1],"ix":4},"o":{"a":0,"k":100,"ix":5},"r":1,"nm":"Fill 1","mn":"ADBE Vector Graphic - Fill","hd":false},{"ty":"tr","p":{"a":0,"k":[315.895,299.49],"ix":2},"a":{"a":0,"k":[0,0],"ix":1},"s":{"a":0,"k":[100,100],"ix":3},"r":{"a":0,"k":0,"ix":6},"o":{"a":0,"k":100,"ix":7},"sk":{"a":0,"k":0,"ix":4},"sa":{"a":0,"k":0,"ix":5},"nm":"Transform"}],"nm":"Group 20","np":9,"cix":2,"ix":11,"mn":"ADBE Vector Group","hd":false},{"ty":"gr","it":[{"ind":0,"ty":"sh","ix":1,"ks":{"a":0,"k":{"i":[[0,0],[0,0],[0,0],[0,0],[0,0],[0,0]],"o":[[0,0],[0,0],[0,0],[0,0],[0,0],[0,0]],"v":[[-9.922,-32.516],[-32.516,-9.922],[-18.829,18.828],[9.921,32.516],[32.516,9.921],[18.828,-18.828]],"c":true},"ix":2},"nm":"Path 1","mn":"ADBE Vector Shape - Group","hd":false},{"ind":1,"ty":"sh","ix":2,"ks":{"a":0,"k":{"i":[[0,0],[0,0],[0,0],[0,0],[0,0],[0,0]],"o":[[0,0],[0,0],[0,0],[0,0],[0,0],[0,0]],"v":[[-7.695,-19.876],[11.035,-10.97],[19.941,7.76],[7.825,19.876],[-10.904,10.969],[-19.811,-7.761]],"c":true},"ix":2},"nm":"Path 2","mn":"ADBE Vector Shape - Group","hd":false},{"ty":"mm","mm":1,"nm":"Merge Paths 1","mn":"ADBE Vector Filter - Merge","hd":false},{"ty":"fl","c":{"a":0,"k":[0,0,0,1],"ix":4},"o":{"a":0,"k":100,"ix":5},"r":1,"nm":"Fill 1","mn":"ADBE Vector Graphic - Fill","hd":false},{"ty":"tr","p":{"a":0,"k":[249.357,262.226],"ix":2},"a":{"a":0,"k":[0,0],"ix":1},"s":{"a":0,"k":[100,100],"ix":3},"r":{"a":0,"k":0,"ix":6},"o":{"a":0,"k":100,"ix":7},"sk":{"a":0,"k":0,"ix":4},"sa":{"a":0,"k":0,"ix":5},"nm":"Transform"}],"nm":"Group 21","np":4,"cix":2,"ix":12,"mn":"ADBE Vector Group","hd":false},{"ty":"gr","it":[{"ind":0,"ty":"sh","ix":1,"ks":{"a":0,"k":{"i":[[0,0],[0,0],[0,0],[0,0],[0,0],[0,0]],"o":[[0,0],[0,0],[0,0],[0,0],[0,0],[0,0]],"v":[[-14.866,14.898],[-26.196,-8.874],[-8.841,-26.163],[14.866,-14.899],[26.197,8.874],[8.841,26.164]],"c":true},"ix":2},"nm":"Path 1","mn":"ADBE Vector Shape - Group","hd":false},{"ty":"fl","c":{"a":0,"k":[0.658999992819,0.819999964097,0.33300000359,1],"ix":4},"o":{"a":0,"k":100,"ix":5},"r":1,"nm":"Fill 1","mn":"ADBE Vector Graphic - Fill","hd":false},{"ty":"tr","p":{"a":0,"k":[249.39,262.227],"ix":2},"a":{"a":0,"k":[0,0],"ix":1},"s":{"a":0,"k":[100,100],"ix":3},"r":{"a":0,"k":0,"ix":6},"o":{"a":0,"k":100,"ix":7},"sk":{"a":0,"k":0,"ix":4},"sa":{"a":0,"k":0,"ix":5},"nm":"Transform"}],"nm":"Group 22","np":2,"cix":2,"ix":13,"mn":"ADBE Vector Group","hd":false},{"ty":"gr","it":[{"ind":0,"ty":"sh","ix":1,"ks":{"a":0,"k":{"i":[[0,0],[0,0],[0,0],[0,0],[0,0],[0,0],[0,0],[0,0],[0,0],[0,0],[0,0],[0,0]],"o":[[0,0],[0,0],[0,0],[0,0],[0,0],[0,0],[0,0],[0,0],[0,0],[0,0],[0,0],[0,0]],"v":[[-11.132,-33.335],[-18.533,-25.934],[-25.934,-18.533],[-33.334,-11.133],[-25.934,-3.732],[3.733,25.934],[11.134,33.335],[18.534,25.934],[25.934,18.534],[33.335,11.133],[25.934,3.733],[-3.733,-25.934]],"c":true},"ix":2},"nm":"Path 1","mn":"ADBE Vector Shape - Group","hd":false},{"ind":1,"ty":"sh","ix":2,"ks":{"a":0,"k":{"i":[[0,0],[0,0],[0,0],[0,0]],"o":[[0,0],[0,0],[0,0],[0,0]],"v":[[-11.132,-18.468],[18.534,11.199],[11.134,18.6],[-18.533,-11.067]],"c":true},"ix":2},"nm":"Path 2","mn":"ADBE Vector Shape - Group","hd":false},{"ty":"mm","mm":1,"nm":"Merge Paths 1","mn":"ADBE Vector Filter - Merge","hd":false},{"ty":"fl","c":{"a":0,"k":[0,0,0,1],"ix":4},"o":{"a":0,"k":100,"ix":5},"r":1,"nm":"Fill 1","mn":"ADBE Vector Graphic - Fill","hd":false},{"ty":"tr","p":{"a":0,"k":[286.457,225.192],"ix":2},"a":{"a":0,"k":[0,0],"ix":1},"s":{"a":0,"k":[100,100],"ix":3},"r":{"a":0,"k":0,"ix":6},"o":{"a":0,"k":100,"ix":7},"sk":{"a":0,"k":0,"ix":4},"sa":{"a":0,"k":0,"ix":5},"nm":"Transform"}],"nm":"Group 23","np":4,"cix":2,"ix":14,"mn":"ADBE Vector Group","hd":false},{"ty":"gr","it":[{"ind":0,"ty":"sh","ix":1,"ks":{"a":0,"k":{"i":[[0,0],[0,0],[0,0],[0,0]],"o":[[0,0],[0,0],[0,0],[0,0]],"v":[[-25.932,-11.114],[-11.115,-25.932],[25.932,11.114],[11.115,25.932]],"c":true},"ix":2},"nm":"Path 1","mn":"ADBE Vector Shape - Group","hd":false},{"ty":"fl","c":{"a":0,"k":[0.658999992819,0.819999964097,0.33300000359,1],"ix":4},"o":{"a":0,"k":100,"ix":5},"r":1,"nm":"Fill 1","mn":"ADBE Vector Graphic - Fill","hd":false},{"ty":"tr","p":{"a":0,"k":[286.38,225.22],"ix":2},"a":{"a":0,"k":[0,0],"ix":1},"s":{"a":0,"k":[100,100],"ix":3},"r":{"a":0,"k":0,"ix":6},"o":{"a":0,"k":100,"ix":7},"sk":{"a":0,"k":0,"ix":4},"sa":{"a":0,"k":0,"ix":5},"nm":"Transform"}],"nm":"Group 24","np":2,"cix":2,"ix":15,"mn":"ADBE Vector Group","hd":false},{"ty":"gr","it":[{"ind":0,"ty":"sh","ix":1,"ks":{"a":0,"k":{"i":[[0,0],[0,0],[0,0],[0,0],[0,0],[0,0],[0,0],[0,0],[-2.226,2.751],[-2.816,2.947],[-1.834,1.637],[-1.965,1.965],[-1.899,2.292],[0,0],[0,0],[0,0],[-6.026,6.288],[-3.93,3.275],[-1.31,1.114],[-2.62,2.685],[-1.899,1.703],[0,0],[0,0],[0,0]],"o":[[0,0],[0,0],[0,0],[0,0],[0,0],[0,0],[0,0],[2.488,-2.816],[2.751,-3.406],[1.44,-1.572],[1.898,-1.703],[1.638,-1.768],[0,0],[0,0],[0,0],[5.566,-7.531],[3.209,-3.339],[1.309,-1.113],[3.078,-2.62],[1.965,-1.964],[0,0],[0,0],[0,0],[0,0]],"v":[[-1.997,-99.577],[-9.397,-92.177],[-90.933,-10.707],[-98.333,-3.306],[-90.933,4.094],[-3.308,91.719],[4.552,99.577],[11.952,91.26],[19.024,82.812],[27.211,73.185],[32.189,68.47],[37.951,63.034],[43.256,57.074],[43.452,56.813],[43.649,56.551],[44.435,55.503],[61.266,34.611],[72.137,24.919],[76.132,21.579],[84.58,13.524],[90.212,8.023],[98.333,0.622],[90.539,-7.171],[5.402,-92.307]],"c":true},"ix":2},"nm":"Path 1","mn":"ADBE Vector Shape - Group","hd":false},{"ind":1,"ty":"sh","ix":2,"ks":{"a":0,"k":{"i":[[0,0],[0,0],[4.912,-4.19],[4.845,-4.976],[5.829,-7.858],[1.636,-1.769],[3.406,-3.603],[5.305,-5.96],[0,0]],"o":[[0,0],[-4.715,4.322],[-5.305,4.52],[-6.812,7.074],[-1.571,1.834],[-3.471,3.601],[-5.501,5.828],[0,0],[0,0]],"v":[[-1.997,-84.776],[83.139,0.361],[69.255,13.654],[53.604,27.407],[35.135,50.329],[30.355,55.765],[19.614,65.982],[4.158,84.319],[-83.532,-3.241]],"c":true},"ix":2},"nm":"Path 2","mn":"ADBE Vector Shape - Group","hd":false},{"ty":"mm","mm":1,"nm":"Merge Paths 1","mn":"ADBE Vector Filter - Merge","hd":false},{"ty":"fl","c":{"a":0,"k":[0,0,0,1],"ix":4},"o":{"a":0,"k":100,"ix":5},"r":1,"nm":"Fill 1","mn":"ADBE Vector Graphic - Fill","hd":false},{"ty":"tr","p":{"a":0,"k":[277.321,261.833],"ix":2},"a":{"a":0,"k":[0,0],"ix":1},"s":{"a":0,"k":[100,100],"ix":3},"r":{"a":0,"k":0,"ix":6},"o":{"a":0,"k":100,"ix":7},"sk":{"a":0,"k":0,"ix":4},"sa":{"a":0,"k":0,"ix":5},"nm":"Transform"}],"nm":"Group 25","np":4,"cix":2,"ix":16,"mn":"ADBE Vector Group","hd":false},{"ty":"gr","it":[{"ind":0,"ty":"sh","ix":1,"ks":{"a":0,"k":{"i":[[0,0],[0,0],[0,0],[0,0],[1.965,-1.965],[2.946,-2.488],[1.31,-1.048],[3.472,-3.538],[5.435,-7.335],[0,0],[0,0],[1.572,-1.637],[1.834,-1.637],[1.572,-1.769],[2.817,-3.536],[2.357,-2.75],[0,0]],"o":[[0,0],[0,0],[0,0],[-1.964,1.767],[-2.553,2.553],[-1.311,1.113],[-4.06,3.339],[-6.287,6.483],[0,0],[0,0],[-1.834,2.161],[-1.768,1.834],[-1.898,1.703],[-2.947,3.143],[-2.226,2.751],[0,0],[0,0]],"v":[[-90.835,-3.143],[-1.899,-92.079],[90.835,0.655],[86.773,4.323],[80.944,9.955],[72.759,17.682],[68.829,20.957],[57.499,31.043],[40.21,52.458],[39.358,53.571],[39.293,53.702],[34.25,59.399],[28.749,64.573],[23.51,69.616],[15.061,79.57],[8.186,87.887],[4.519,92.079]],"c":true},"ix":2},"nm":"Path 1","mn":"ADBE Vector Shape - Group","hd":false},{"ty":"fl","c":{"a":0,"k":[0.481999984442,0.819999964097,0.33300000359,1],"ix":4},"o":{"a":0,"k":100,"ix":5},"r":1,"nm":"Fill 1","mn":"ADBE Vector Graphic - Fill","hd":false},{"ty":"tr","p":{"a":0,"k":[277.223,261.735],"ix":2},"a":{"a":0,"k":[0,0],"ix":1},"s":{"a":0,"k":[100,100],"ix":3},"r":{"a":0,"k":0,"ix":6},"o":{"a":0,"k":100,"ix":7},"sk":{"a":0,"k":0,"ix":4},"sa":{"a":0,"k":0,"ix":5},"nm":"Transform"}],"nm":"Group 26","np":2,"cix":2,"ix":17,"mn":"ADBE Vector Group","hd":false},{"ty":"gr","it":[{"ind":0,"ty":"sh","ix":1,"ks":{"a":0,"k":{"i":[[0,0],[0,0],[0,0],[0,0]],"o":[[0,0],[0,0],[0,0],[0,0]],"v":[[33.489,-29.785],[29.784,-33.49],[39.047,-42.75],[42.751,-39.047]],"c":true},"ix":2},"nm":"Path 1","mn":"ADBE Vector Shape - Group","hd":false},{"ind":1,"ty":"sh","ix":2,"ks":{"a":0,"k":{"i":[[0,0],[0,0],[0,0],[0,0]],"o":[[0,0],[0,0],[0,0],[0,0]],"v":[[20.522,-16.819],[16.818,-20.522],[26.08,-29.785],[29.784,-26.079]],"c":true},"ix":2},"nm":"Path 2","mn":"ADBE Vector Shape - Group","hd":false},{"ind":2,"ty":"sh","ix":3,"ks":{"a":0,"k":{"i":[[0,0],[0,0],[0,0],[0,0]],"o":[[0,0],[0,0],[0,0],[0,0]],"v":[[7.556,-3.852],[3.852,-7.556],[13.114,-16.819],[16.818,-13.113]],"c":true},"ix":2},"nm":"Path 3","mn":"ADBE Vector Shape - Group","hd":false},{"ind":3,"ty":"sh","ix":4,"ks":{"a":0,"k":{"i":[[0,0],[0,0],[0,0],[0,0]],"o":[[0,0],[0,0],[0,0],[0,0]],"v":[[-5.41,9.113],[-9.115,5.409],[0.148,-3.852],[3.852,-0.147]],"c":true},"ix":2},"nm":"Path 4","mn":"ADBE Vector Shape - Group","hd":false},{"ind":4,"ty":"sh","ix":5,"ks":{"a":0,"k":{"i":[[0,0],[0,0],[0,0],[0,0]],"o":[[0,0],[0,0],[0,0],[0,0]],"v":[[-18.376,22.08],[-22.081,18.375],[-12.82,9.114],[-9.115,12.819]],"c":true},"ix":2},"nm":"Path 5","mn":"ADBE Vector Shape - Group","hd":false},{"ind":5,"ty":"sh","ix":6,"ks":{"a":0,"k":{"i":[[0,0],[0,0],[0,0],[0,0]],"o":[[0,0],[0,0],[0,0],[0,0]],"v":[[-31.343,35.046],[-35.047,31.342],[-25.786,22.08],[-22.081,25.784]],"c":true},"ix":2},"nm":"Path 6","mn":"ADBE Vector Shape - Group","hd":false},{"ind":6,"ty":"sh","ix":7,"ks":{"a":0,"k":{"i":[[0,0],[0,0],[0,0],[0,0]],"o":[[0,0],[0,0],[0,0],[0,0]],"v":[[-39.046,42.75],[-42.751,39.046],[-38.752,35.047],[-35.047,38.751]],"c":true},"ix":2},"nm":"Path 7","mn":"ADBE Vector Shape - Group","hd":false},{"ty":"mm","mm":1,"nm":"Merge Paths 1","mn":"ADBE Vector Filter - Merge","hd":false},{"ty":"fl","c":{"a":0,"k":[0,0,0,1],"ix":4},"o":{"a":0,"k":100,"ix":5},"r":1,"nm":"Fill 1","mn":"ADBE Vector Graphic - Fill","hd":false},{"ty":"tr","p":{"a":0,"k":[276.601,279.843],"ix":2},"a":{"a":0,"k":[0,0],"ix":1},"s":{"a":0,"k":[100,100],"ix":3},"r":{"a":0,"k":0,"ix":6},"o":{"a":0,"k":100,"ix":7},"sk":{"a":0,"k":0,"ix":4},"sa":{"a":0,"k":0,"ix":5},"nm":"Transform"}],"nm":"Group 27","np":9,"cix":2,"ix":18,"mn":"ADBE Vector Group","hd":false},{"ty":"gr","it":[{"ind":0,"ty":"sh","ix":1,"ks":{"a":0,"k":{"i":[[0,0],[0,0],[0,0],[0,0],[0,0],[0,0]],"o":[[0,0],[0,0],[0,0],[0,0],[0,0],[0,0]],"v":[[-9.922,-32.516],[-32.516,-9.921],[-18.829,18.829],[9.921,32.516],[32.516,9.923],[18.828,-18.827]],"c":true},"ix":2},"nm":"Path 1","mn":"ADBE Vector Shape - Group","hd":false},{"ind":1,"ty":"sh","ix":2,"ks":{"a":0,"k":{"i":[[0,0],[0,0],[0,0],[0,0],[0,0],[0,0]],"o":[[0,0],[0,0],[0,0],[0,0],[0,0],[0,0]],"v":[[-7.695,-19.875],[11.035,-10.969],[19.941,7.76],[7.826,19.876],[-10.904,10.97],[-19.811,-7.76]],"c":true},"ix":2},"nm":"Path 2","mn":"ADBE Vector Shape - Group","hd":false},{"ty":"mm","mm":1,"nm":"Merge Paths 1","mn":"ADBE Vector Filter - Merge","hd":false},{"ty":"fl","c":{"a":0,"k":[0,0,0,1],"ix":4},"o":{"a":0,"k":100,"ix":5},"r":1,"nm":"Fill 1","mn":"ADBE Vector Graphic - Fill","hd":false},{"ty":"tr","p":{"a":0,"k":[210.064,242.579],"ix":2},"a":{"a":0,"k":[0,0],"ix":1},"s":{"a":0,"k":[100,100],"ix":3},"r":{"a":0,"k":0,"ix":6},"o":{"a":0,"k":100,"ix":7},"sk":{"a":0,"k":0,"ix":4},"sa":{"a":0,"k":0,"ix":5},"nm":"Transform"}],"nm":"Group 28","np":4,"cix":2,"ix":19,"mn":"ADBE Vector Group","hd":false},{"ty":"gr","it":[{"ind":0,"ty":"sh","ix":1,"ks":{"a":0,"k":{"i":[[0,0],[0,0],[0,0],[0,0],[0,0],[0,0]],"o":[[0,0],[0,0],[0,0],[0,0],[0,0],[0,0]],"v":[[-14.866,14.9],[-26.196,-8.874],[-8.841,-26.163],[14.866,-14.898],[26.196,8.875],[8.841,26.163]],"c":true},"ix":2},"nm":"Path 1","mn":"ADBE Vector Shape - Group","hd":false},{"ty":"fl","c":{"a":0,"k":[0.658999992819,0.819999964097,0.33300000359,1],"ix":4},"o":{"a":0,"k":100,"ix":5},"r":1,"nm":"Fill 1","mn":"ADBE Vector Graphic - Fill","hd":false},{"ty":"tr","p":{"a":0,"k":[210.096,242.579],"ix":2},"a":{"a":0,"k":[0,0],"ix":1},"s":{"a":0,"k":[100,100],"ix":3},"r":{"a":0,"k":0,"ix":6},"o":{"a":0,"k":100,"ix":7},"sk":{"a":0,"k":0,"ix":4},"sa":{"a":0,"k":0,"ix":5},"nm":"Transform"}],"nm":"Group 29","np":2,"cix":2,"ix":20,"mn":"ADBE Vector Group","hd":false},{"ty":"gr","it":[{"ind":0,"ty":"sh","ix":1,"ks":{"a":0,"k":{"i":[[0,0],[0,0],[0,0],[0,0],[0,0],[0,0],[0,0],[0,0],[0,0],[0,0],[0,0],[0,0]],"o":[[0,0],[0,0],[0,0],[0,0],[0,0],[0,0],[0,0],[0,0],[0,0],[0,0],[0,0],[0,0]],"v":[[-11.133,-33.334],[-18.533,-25.934],[-25.934,-18.533],[-33.334,-11.133],[-25.934,-3.732],[3.733,25.934],[11.134,33.334],[18.534,25.934],[25.934,18.534],[33.334,11.134],[25.934,3.733],[-3.733,-25.934]],"c":true},"ix":2},"nm":"Path 1","mn":"ADBE Vector Shape - Group","hd":false},{"ind":1,"ty":"sh","ix":2,"ks":{"a":0,"k":{"i":[[0,0],[0,0],[0,0],[0,0]],"o":[[0,0],[0,0],[0,0],[0,0]],"v":[[-11.133,-18.468],[18.534,11.199],[11.134,18.6],[-18.533,-11.067]],"c":true},"ix":2},"nm":"Path 2","mn":"ADBE Vector Shape - Group","hd":false},{"ty":"mm","mm":1,"nm":"Merge Paths 1","mn":"ADBE Vector Filter - Merge","hd":false},{"ty":"fl","c":{"a":0,"k":[0,0,0,1],"ix":4},"o":{"a":0,"k":100,"ix":5},"r":1,"nm":"Fill 1","mn":"ADBE Vector Graphic - Fill","hd":false},{"ty":"tr","p":{"a":0,"k":[247.163,205.544],"ix":2},"a":{"a":0,"k":[0,0],"ix":1},"s":{"a":0,"k":[100,100],"ix":3},"r":{"a":0,"k":0,"ix":6},"o":{"a":0,"k":100,"ix":7},"sk":{"a":0,"k":0,"ix":4},"sa":{"a":0,"k":0,"ix":5},"nm":"Transform"}],"nm":"Group 30","np":4,"cix":2,"ix":21,"mn":"ADBE Vector Group","hd":false},{"ty":"gr","it":[{"ind":0,"ty":"sh","ix":1,"ks":{"a":0,"k":{"i":[[0,0],[0,0],[0,0],[0,0]],"o":[[0,0],[0,0],[0,0],[0,0]],"v":[[-25.932,-11.114],[-11.113,-25.932],[25.932,11.114],[11.113,25.932]],"c":true},"ix":2},"nm":"Path 1","mn":"ADBE Vector Shape - Group","hd":false},{"ty":"fl","c":{"a":0,"k":[0.658999992819,0.819999964097,0.33300000359,1],"ix":4},"o":{"a":0,"k":100,"ix":5},"r":1,"nm":"Fill 1","mn":"ADBE Vector Graphic - Fill","hd":false},{"ty":"tr","p":{"a":0,"k":[247.086,205.574],"ix":2},"a":{"a":0,"k":[0,0],"ix":1},"s":{"a":0,"k":[100,100],"ix":3},"r":{"a":0,"k":0,"ix":6},"o":{"a":0,"k":100,"ix":7},"sk":{"a":0,"k":0,"ix":4},"sa":{"a":0,"k":0,"ix":5},"nm":"Transform"}],"nm":"Group 31","np":2,"cix":2,"ix":22,"mn":"ADBE Vector Group","hd":false},{"ty":"gr","it":[{"ind":0,"ty":"sh","ix":1,"ks":{"a":0,"k":{"i":[[0,0],[0,0],[0,0],[0,0],[0,0],[0,0],[0,0],[0,0],[-0.72,0.917],[-1.441,1.769],[0,0],[0,0],[0,0]],"o":[[0,0],[0,0],[0,0],[0,0],[0,0],[0,0],[0,0],[0.72,-0.917],[1.507,-1.833],[0,0],[0,0],[0,0],[0,0]],"v":[[1.638,-21.677],[-5.762,-14.277],[-13.163,-6.876],[-20.629,0.524],[-13.228,7.925],[-7.661,13.491],[0.525,21.677],[7.86,12.705],[10.021,10.019],[14.409,4.649],[20.63,-2.685],[13.82,-9.496],[9.038,-14.277]],"c":true},"ix":2},"nm":"Path 1","mn":"ADBE Vector Shape - Group","hd":false},{"ind":1,"ty":"sh","ix":2,"ks":{"a":0,"k":{"i":[[0,0],[0,0],[2.226,-2.751],[0,0]],"o":[[0,0],[-2.292,2.686],[0,0],[0,0]],"v":[[1.638,-6.876],[6.419,-2.096],[-0.26,6.091],[-5.828,0.524]],"c":true},"ix":2},"nm":"Path 2","mn":"ADBE Vector Shape - Group","hd":false},{"ty":"mm","mm":1,"nm":"Merge Paths 1","mn":"ADBE Vector Filter - Merge","hd":false},{"ty":"fl","c":{"a":0,"k":[0,0,0,1],"ix":4},"o":{"a":0,"k":100,"ix":5},"r":1,"nm":"Fill 1","mn":"ADBE Vector Graphic - Fill","hd":false},{"ty":"tr","p":{"a":0,"k":[286.26,334.691],"ix":2},"a":{"a":0,"k":[0,0],"ix":1},"s":{"a":0,"k":[100,100],"ix":3},"r":{"a":0,"k":0,"ix":6},"o":{"a":0,"k":100,"ix":7},"sk":{"a":0,"k":0,"ix":4},"sa":{"a":0,"k":0,"ix":5},"nm":"Transform"}],"nm":"Group 32","np":4,"cix":2,"ix":23,"mn":"ADBE Vector Group","hd":false},{"ty":"gr","it":[{"ind":0,"ty":"sh","ix":1,"ks":{"a":0,"k":{"i":[[0,0],[0,0],[0,0],[0,0],[1.442,-1.833],[0.721,-0.917],[0,0]],"o":[[0,0],[0,0],[0,0],[-1.507,1.769],[-0.719,0.917],[0,0],[0,0]],"v":[[-13.36,0.688],[1.441,-14.113],[13.36,-2.194],[10.283,1.473],[5.828,6.909],[3.667,9.594],[0,14.113]],"c":true},"ix":2},"nm":"Path 1","mn":"ADBE Vector Shape - Group","hd":false},{"ty":"fl","c":{"a":0,"k":[0.658999992819,0.819999964097,0.33300000359,1],"ix":4},"o":{"a":0,"k":100,"ix":5},"r":1,"nm":"Fill 1","mn":"ADBE Vector Graphic - Fill","hd":false},{"ty":"tr","p":{"a":0,"k":[286.391,334.527],"ix":2},"a":{"a":0,"k":[0,0],"ix":1},"s":{"a":0,"k":[100,100],"ix":3},"r":{"a":0,"k":0,"ix":6},"o":{"a":0,"k":100,"ix":7},"sk":{"a":0,"k":0,"ix":4},"sa":{"a":0,"k":0,"ix":5},"nm":"Transform"}],"nm":"Group 33","np":2,"cix":2,"ix":24,"mn":"ADBE Vector Group","hd":false},{"ty":"gr","it":[{"ind":0,"ty":"sh","ix":1,"ks":{"a":0,"k":{"i":[[0,0],[0,0],[0,0],[0,0],[0,0],[0,0],[0,0],[0,0],[-2.947,3.143],[-1.179,1.114],[0,0],[0,0],[0,0]],"o":[[0,0],[0,0],[0,0],[0,0],[0,0],[0,0],[0,0],[3.536,-4.584],[0.982,-0.983],[0,0],[0,0],[0,0],[0,0]],"v":[[6.157,-24.297],[-1.309,-16.897],[-16.111,-2.096],[-23.51,5.37],[-16.111,12.77],[-12.966,15.914],[-4.583,24.297],[2.686,14.932],[12.247,3.667],[15.457,0.523],[23.51,-6.877],[15.784,-14.605],[13.492,-16.897]],"c":true},"ix":2},"nm":"Path 1","mn":"ADBE Vector Shape - Group","hd":false},{"ind":1,"ty":"sh","ix":2,"ks":{"a":0,"k":{"i":[[0,0],[0,0],[1.179,-1.244],[3.209,-4.191],[0,0]],"o":[[0,0],[-1.244,1.178],[-3.668,3.799],[0,0],[0,0]],"v":[[6.157,-9.496],[8.449,-7.204],[4.782,-3.603],[-5.5,8.448],[-8.645,5.305]],"c":true},"ix":2},"nm":"Path 2","mn":"ADBE Vector Shape - Group","hd":false},{"ty":"mm","mm":1,"nm":"Merge Paths 1","mn":"ADBE Vector Filter - Merge","hd":false},{"ty":"fl","c":{"a":0,"k":[0,0,0,1],"ix":4},"o":{"a":0,"k":100,"ix":5},"r":1,"nm":"Fill 1","mn":"ADBE Vector Graphic - Fill","hd":false},{"ty":"tr","p":{"a":0,"k":[326.209,292.843],"ix":2},"a":{"a":0,"k":[0,0],"ix":1},"s":{"a":0,"k":[100,100],"ix":3},"r":{"a":0,"k":0,"ix":6},"o":{"a":0,"k":100,"ix":7},"sk":{"a":0,"k":0,"ix":4},"sa":{"a":0,"k":0,"ix":5},"nm":"Transform"}],"nm":"Group 34","np":4,"cix":2,"ix":25,"mn":"ADBE Vector Group","hd":false},{"ty":"gr","it":[{"ind":0,"ty":"sh","ix":1,"ks":{"a":0,"k":{"i":[[0,0],[0,0],[0,0],[0,0],[1.048,-1.048],[3.667,-4.716],[0,0]],"o":[[0,0],[0,0],[0,0],[-1.311,1.179],[-3.144,3.209],[0,0],[0,0]],"v":[[-16.045,5.599],[6.156,-16.602],[16.045,-6.779],[12.051,-3.11],[8.579,0.229],[-1.375,11.887],[-5.043,16.602]],"c":true},"ix":2},"nm":"Path 1","mn":"ADBE Vector Shape - Group","hd":false},{"ty":"fl","c":{"a":0,"k":[0.658999992819,0.819999964097,0.33300000359,1],"ix":4},"o":{"a":0,"k":100,"ix":5},"r":1,"nm":"Fill 1","mn":"ADBE Vector Graphic - Fill","hd":false},{"ty":"tr","p":{"a":0,"k":[326.144,292.613],"ix":2},"a":{"a":0,"k":[0,0],"ix":1},"s":{"a":0,"k":[100,100],"ix":3},"r":{"a":0,"k":0,"ix":6},"o":{"a":0,"k":100,"ix":7},"sk":{"a":0,"k":0,"ix":4},"sa":{"a":0,"k":0,"ix":5},"nm":"Transform"}],"nm":"Group 35","np":2,"cix":2,"ix":26,"mn":"ADBE Vector Group","hd":false},{"ty":"gr","it":[{"ind":0,"ty":"sh","ix":1,"ks":{"a":0,"k":{"i":[[0,0],[0,0],[0,0],[0,0],[0,0],[0,0],[0,0],[0,0],[0,0],[0,0],[-3.536,4.322],[-2.816,2.946],[-1.834,1.638],[-1.965,1.965],[-1.899,2.293],[0,0],[0,0],[0,0],[-6.025,6.287],[-3.929,3.275],[-1.309,1.113],[-1.638,1.573],[0,0],[0,0],[0,0]],"o":[[0,0],[0,0],[0,0],[0,0],[0,0],[0,0],[0,0],[0,0],[0,0],[4.191,-4.192],[2.751,-3.406],[1.441,-1.572],[1.898,-1.702],[1.637,-1.769],[0,0],[0,0],[0,0],[5.566,-7.531],[3.209,-3.34],[1.31,-1.113],[1.375,-1.179],[0,0],[0,0],[0,0],[0,0]],"v":[[-16.602,-115.066],[-24.002,-107.665],[-105.537,-26.197],[-112.937,-18.796],[-105.537,-11.331],[12.41,106.617],[20.858,115.065],[28.128,105.634],[29.176,104.259],[32.385,100.068],[43.714,87.102],[51.9,77.474],[56.878,72.758],[62.641,67.323],[67.945,61.363],[68.142,61.102],[68.338,60.839],[69.124,59.791],[85.955,38.9],[96.826,29.207],[100.821,25.868],[105.209,21.872],[112.937,14.472],[105.405,6.941],[-9.202,-107.665]],"c":true},"ix":2},"nm":"Path 1","mn":"ADBE Vector Shape - Group","hd":false},{"ind":1,"ty":"sh","ix":2,"ks":{"a":0,"k":{"i":[[0,0],[0,0],[1.376,-1.179],[4.846,-4.977],[5.829,-7.859],[1.637,-1.768],[3.405,-3.602],[7.204,-7.074],[1.571,-2.03],[0,0]],"o":[[0,0],[-1.244,1.245],[-5.304,4.519],[-6.812,7.073],[-1.571,1.834],[-3.471,3.602],[-6.877,7.335],[-1.571,2.03],[0,0],[0,0]],"v":[[-16.602,-100.266],[97.874,14.21],[93.944,17.813],[78.293,31.565],[59.824,54.487],[55.044,59.922],[44.304,70.139],[24.591,92.995],[19.876,99.151],[-98.137,-18.73]],"c":true},"ix":2},"nm":"Path 2","mn":"ADBE Vector Shape - Group","hd":false},{"ty":"mm","mm":1,"nm":"Merge Paths 1","mn":"ADBE Vector Filter - Merge","hd":false},{"ty":"fl","c":{"a":0,"k":[0,0,0,1],"ix":4},"o":{"a":0,"k":100,"ix":5},"r":1,"nm":"Fill 1","mn":"ADBE Vector Graphic - Fill","hd":false},{"ty":"tr","p":{"a":0,"k":[252.632,257.675],"ix":2},"a":{"a":0,"k":[0,0],"ix":1},"s":{"a":0,"k":[100,100],"ix":3},"r":{"a":0,"k":0,"ix":6},"o":{"a":0,"k":100,"ix":7},"sk":{"a":0,"k":0,"ix":4},"sa":{"a":0,"k":0,"ix":5},"nm":"Transform"}],"nm":"Group 36","np":4,"cix":2,"ix":27,"mn":"ADBE Vector Group","hd":false},{"ty":"gr","it":[{"ind":0,"ty":"sh","ix":1,"ks":{"a":0,"k":{"i":[[0,0],[0,0],[0,0],[0,0],[1.31,-1.113],[1.309,-1.113],[3.472,-3.536],[5.436,-7.335],[0,0],[0,0],[1.573,-1.637],[1.834,-1.637],[1.573,-1.768],[2.816,-3.536],[4.061,-4.06],[0,0]],"o":[[0,0],[0,0],[0,0],[-1.507,1.506],[-1.31,1.113],[-4.061,3.341],[-6.287,6.483],[0,0],[0,0],[-1.834,2.161],[-1.767,1.833],[-1.899,1.703],[-2.946,3.144],[-3.471,4.323],[0,0],[0,0]],"v":[[-105.438,-18.436],[-16.503,-107.371],[105.438,14.571],[101.576,18.305],[97.383,22.102],[93.455,25.443],[82.123,35.529],[64.834,56.943],[63.984,58.056],[63.917,58.188],[58.874,63.885],[53.373,69.058],[48.135,74.102],[39.687,84.055],[28.554,96.826],[20.368,107.37]],"c":true},"ix":2},"nm":"Path 1","mn":"ADBE Vector Shape - Group","hd":false},{"ty":"fl","c":{"a":0,"k":[0.481999984442,0.819999964097,0.33300000359,1],"ix":4},"o":{"a":0,"k":100,"ix":5},"r":1,"nm":"Fill 1","mn":"ADBE Vector Graphic - Fill","hd":false},{"ty":"tr","p":{"a":0,"k":[252.533,257.38],"ix":2},"a":{"a":0,"k":[0,0],"ix":1},"s":{"a":0,"k":[100,100],"ix":3},"r":{"a":0,"k":0,"ix":6},"o":{"a":0,"k":100,"ix":7},"sk":{"a":0,"k":0,"ix":4},"sa":{"a":0,"k":0,"ix":5},"nm":"Transform"}],"nm":"Group 37","np":2,"cix":2,"ix":28,"mn":"ADBE Vector Group","hd":false},{"ty":"gr","it":[{"ind":0,"ty":"sh","ix":1,"ks":{"a":0,"k":{"i":[[0,0],[0,-8.667],[0,0],[-8.667,0],[0,0],[0,8.666],[0,0],[8.666,0]],"o":[[-8.667,0],[0,0],[0,8.666],[0,0],[8.666,0],[0,0],[0,-8.667],[0,0]],"v":[[-94.305,-51.18],[-110.022,-35.462],[-110.022,35.463],[-94.305,51.181],[94.306,51.181],[110.023,35.463],[110.023,-35.462],[94.306,-51.18]],"c":true},"ix":2},"nm":"Path 1","mn":"ADBE Vector Shape - Group","hd":false},{"ind":1,"ty":"sh","ix":2,"ks":{"a":0,"k":{"i":[[14.444,0],[0,0],[0,14.444],[0,0],[-14.444,0],[0,0],[0,-14.445],[0,0]],"o":[[0,0],[-14.444,0],[0,0],[0,-14.445],[0,0],[14.444,0],[0,0],[0,14.444]],"v":[[94.306,61.658],[-94.305,61.658],[-120.501,35.463],[-120.501,-35.462],[-94.305,-61.658],[94.306,-61.658],[120.501,-35.462],[120.501,35.463]],"c":true},"ix":2},"nm":"Path 2","mn":"ADBE Vector Shape - Group","hd":false},{"ty":"mm","mm":1,"nm":"Merge Paths 1","mn":"ADBE Vector Filter - Merge","hd":false},{"ty":"fl","c":{"a":0,"k":[0,0,0,1],"ix":4},"o":{"a":0,"k":100,"ix":5},"r":1,"nm":"Fill 1","mn":"ADBE Vector Graphic - Fill","hd":false},{"ty":"tr","p":{"a":0,"k":[278.074,271.46],"ix":2},"a":{"a":0,"k":[0,0],"ix":1},"s":{"a":0,"k":[100,100],"ix":3},"r":{"a":0,"k":0,"ix":6},"o":{"a":0,"k":100,"ix":7},"sk":{"a":0,"k":0,"ix":4},"sa":{"a":0,"k":0,"ix":5},"nm":"Transform"}],"nm":"Group 38","np":4,"cix":2,"ix":29,"mn":"ADBE Vector Group","hd":false},{"ty":"gr","it":[{"ind":0,"ty":"sh","ix":1,"ks":{"a":0,"k":{"i":[[11.592,0],[0,0],[0,11.592],[0,0],[-11.592,0],[0,0],[0,-11.592],[0,0]],"o":[[0,0],[-11.592,0],[0,0],[0,-11.592],[0,0],[11.592,0],[0,0],[0,11.592]],"v":[[94.306,56.419],[-94.305,56.419],[-115.261,35.463],[-115.261,-35.462],[-94.305,-56.419],[94.306,-56.419],[115.262,-35.462],[115.262,35.463]],"c":true},"ix":2},"nm":"Path 1","mn":"ADBE Vector Shape - Group","hd":false},{"ty":"fl","c":{"a":0,"k":[0.234999997008,0.388000009574,0,1],"ix":4},"o":{"a":0,"k":100,"ix":5},"r":1,"nm":"Fill 1","mn":"ADBE Vector Graphic - Fill","hd":false},{"ty":"tr","p":{"a":0,"k":[278.074,271.46],"ix":2},"a":{"a":0,"k":[0,0],"ix":1},"s":{"a":0,"k":[100,100],"ix":3},"r":{"a":0,"k":0,"ix":6},"o":{"a":0,"k":100,"ix":7},"sk":{"a":0,"k":0,"ix":4},"sa":{"a":0,"k":0,"ix":5},"nm":"Transform"}],"nm":"Group 39","np":2,"cix":2,"ix":30,"mn":"ADBE Vector Group","hd":false},{"ty":"tr","p":{"a":0,"k":[256,256],"ix":2},"a":{"a":0,"k":[256,256],"ix":1},"s":{"a":0,"k":[100,100],"ix":3},"r":{"a":0,"k":0,"ix":6},"o":{"a":0,"k":100,"ix":7},"sk":{"a":0,"k":0,"ix":4},"sa":{"a":0,"k":0,"ix":5},"nm":"Transform"}],"nm":"wallet","np":30,"cix":2,"ix":1,"mn":"ADBE Vector Group","hd":false},{"ty":"gr","it":[{"ty":"gr","it":[{"ind":0,"ty":"sh","ix":1,"ks":{"a":0,"k":{"i":[[27,-5.588],[-23.45,5.795]],"o":[[-18.19,3.765],[23.451,-5.794]],"v":[[-7.405,-19.794],[2.144,19.587]],"c":true},"ix":2},"nm":"Path 1","mn":"ADBE Vector Shape - Group","hd":false},{"ty":"fl","c":{"a":0,"k":[0,0.176000004189,0.301999978458,1],"ix":4},"o":{"a":0,"k":100,"ix":5},"r":1,"nm":"Fill 1","mn":"ADBE Vector Graphic - Fill","hd":false},{"ty":"tr","p":{"a":1,"k":[{"i":{"x":0.667,"y":1},"o":{"x":0.333,"y":0},"n":"0p667_1_0p333_0","t":0,"s":[351.405,348.207],"e":[501.405,496.207],"to":[25,24.6666660308838],"ti":[0,0]},{"i":{"x":0.667,"y":1},"o":{"x":0.333,"y":0},"n":"0p667_1_0p333_0","t":29,"s":[501.405,496.207],"e":[351.405,348.207],"to":[0,0],"ti":[0,0]},{"i":{"x":0.667,"y":1},"o":{"x":0.333,"y":0},"n":"0p667_1_0p333_0","t":41,"s":[351.405,348.207],"e":[501.405,496.207],"to":[0,0],"ti":[0,0]},{"i":{"x":0.667,"y":1},"o":{"x":0.333,"y":0},"n":"0p667_1_0p333_0","t":70,"s":[501.405,496.207],"e":[351.405,348.207],"to":[0,0],"ti":[0,0]},{"i":{"x":0.667,"y":1},"o":{"x":0.333,"y":0},"n":"0p667_1_0p333_0","t":71,"s":[351.405,348.207],"e":[501.405,496.207],"to":[0,0],"ti":[0,0]},{"i":{"x":0.667,"y":1},"o":{"x":0.333,"y":0},"n":"0p667_1_0p333_0","t":89,"s":[501.405,496.207],"e":[351.405,348.207],"to":[0,0],"ti":[0,0]},{"i":{"x":0.667,"y":1},"o":{"x":0.333,"y":0},"n":"0p667_1_0p333_0","t":90,"s":[351.405,348.207],"e":[501.405,496.207],"to":[0,0],"ti":[-25,-24.6666660308838]},{"t":119}],"ix":2},"a":{"a":0,"k":[0,0],"ix":1},"s":{"a":1,"k":[{"i":{"x":[0.667,0.667],"y":[1,1]},"o":{"x":[0.333,0.333],"y":[0,0]},"n":["0p667_1_0p333_0","0p667_1_0p333_0"],"t":0,"s":[100,100],"e":[100,100]},{"i":{"x":[0.667,0.667],"y":[1,1]},"o":{"x":[0.333,0.333],"y":[0,0]},"n":["0p667_1_0p333_0","0p667_1_0p333_0"],"t":20,"s":[100,100],"e":[0,0]},{"i":{"x":[0.667,0.667],"y":[1,1]},"o":{"x":[0.333,0.333],"y":[0,0]},"n":["0p667_1_0p333_0","0p667_1_0p333_0"],"t":29,"s":[0,0],"e":[100,100]},{"i":{"x":[0.667,0.667],"y":[1,1]},"o":{"x":[0.333,0.333],"y":[0,0]},"n":["0p667_1_0p333_0","0p667_1_0p333_0"],"t":41,"s":[100,100],"e":[100,100]},{"i":{"x":[0.667,0.667],"y":[1,1]},"o":{"x":[0.333,0.333],"y":[0,0]},"n":["0p667_1_0p333_0","0p667_1_0p333_0"],"t":50,"s":[100,100],"e":[0,0]},{"i":{"x":[0.667,0.667],"y":[1,1]},"o":{"x":[0.333,0.333],"y":[0,0]},"n":["0p667_1_0p333_0","0p667_1_0p333_0"],"t":70,"s":[0,0],"e":[100,100]},{"i":{"x":[0.667,0.667],"y":[1,1]},"o":{"x":[0.333,0.333],"y":[0,0]},"n":["0p667_1_0p333_0","0p667_1_0p333_0"],"t":71,"s":[100,100],"e":[100,100]},{"i":{"x":[0.667,0.667],"y":[1,1]},"o":{"x":[0.333,0.333],"y":[0,0]},"n":["0p667_1_0p333_0","0p667_1_0p333_0"],"t":80,"s":[100,100],"e":[0,0]},{"i":{"x":[0.667,0.667],"y":[1,1]},"o":{"x":[0.333,0.333],"y":[0,0]},"n":["0p667_1_0p333_0","0p667_1_0p333_0"],"t":89,"s":[0,0],"e":[100,100]},{"i":{"x":[0.667,0.667],"y":[1,1]},"o":{"x":[0.333,0.333],"y":[0,0]},"n":["0p667_1_0p333_0","0p667_1_0p333_0"],"t":90,"s":[100,100],"e":[100,100]},{"i":{"x":[0.667,0.667],"y":[1,1]},"o":{"x":[0.333,0.333],"y":[0,0]},"n":["0p667_1_0p333_0","0p667_1_0p333_0"],"t":106,"s":[100,100],"e":[0,0]},{"t":119}],"ix":3},"r":{"a":0,"k":0,"ix":6},"o":{"a":0,"k":100,"ix":7},"sk":{"a":0,"k":0,"ix":4},"sa":{"a":0,"k":0,"ix":5},"nm":"Transform"}],"nm":"Group 1","np":2,"cix":2,"ix":1,"mn":"ADBE Vector Group","hd":false},{"ty":"gr","it":[{"ind":0,"ty":"sh","ix":1,"ks":{"a":0,"k":{"i":[[19.21,2],[-22.825,0]],"o":[[-26.37,-2.746],[22.826,0]],"v":[[4.325,-16.127],[-0.71,18.873]],"c":true},"ix":2},"nm":"Path 1","mn":"ADBE Vector Shape - Group","hd":false},{"ty":"fl","c":{"a":0,"k":[1,0.984000052658,0.090000002992,1],"ix":4},"o":{"a":0,"k":100,"ix":5},"r":1,"nm":"Fill 1","mn":"ADBE Vector Graphic - Fill","hd":false},{"ty":"tr","p":{"a":1,"k":[{"i":{"x":0.667,"y":1},"o":{"x":0.333,"y":0},"n":"0p667_1_0p333_0","t":0,"s":[254.673,201.908],"e":[254.673,7.908],"to":[0,-32.3333320617676],"ti":[0,0]},{"i":{"x":0.667,"y":1},"o":{"x":0.333,"y":0},"n":"0p667_1_0p333_0","t":29,"s":[254.673,7.908],"e":[254.673,201.908],"to":[0,0],"ti":[0,0]},{"i":{"x":0.667,"y":1},"o":{"x":0.333,"y":0},"n":"0p667_1_0p333_0","t":30,"s":[254.673,201.908],"e":[254.673,7.908],"to":[0,0],"ti":[0,0]},{"i":{"x":0.667,"y":1},"o":{"x":0.333,"y":0},"n":"0p667_1_0p333_0","t":59,"s":[254.673,7.908],"e":[254.673,201.908],"to":[0,0],"ti":[0,0]},{"i":{"x":0.667,"y":1},"o":{"x":0.333,"y":0},"n":"0p667_1_0p333_0","t":60,"s":[254.673,201.908],"e":[254.673,7.908],"to":[0,0],"ti":[0,0]},{"i":{"x":0.667,"y":1},"o":{"x":0.333,"y":0},"n":"0p667_1_0p333_0","t":89,"s":[254.673,7.908],"e":[254.673,201.908],"to":[0,0],"ti":[0,0]},{"i":{"x":0.667,"y":1},"o":{"x":0.333,"y":0},"n":"0p667_1_0p333_0","t":90,"s":[254.673,201.908],"e":[254.673,7.908],"to":[0,0],"ti":[0,32.3333320617676]},{"t":119}],"ix":2},"a":{"a":0,"k":[0,0],"ix":1},"s":{"a":1,"k":[{"i":{"x":[0.667,0.667],"y":[1,1]},"o":{"x":[0.333,0.333],"y":[0,0]},"n":["0p667_1_0p333_0","0p667_1_0p333_0"],"t":0,"s":[100,100],"e":[100,100]},{"i":{"x":[0.667,0.667],"y":[1,1]},"o":{"x":[0.333,0.333],"y":[0,0]},"n":["0p667_1_0p333_0","0p667_1_0p333_0"],"t":20,"s":[100,100],"e":[0,0]},{"i":{"x":[0.667,0.667],"y":[1,1]},"o":{"x":[0.333,0.333],"y":[0,0]},"n":["0p667_1_0p333_0","0p667_1_0p333_0"],"t":29,"s":[0,0],"e":[100,100]},{"i":{"x":[0.667,0.667],"y":[1,1]},"o":{"x":[0.333,0.333],"y":[0,0]},"n":["0p667_1_0p333_0","0p667_1_0p333_0"],"t":30,"s":[100,100],"e":[100,100]},{"i":{"x":[0.667,0.667],"y":[1,1]},"o":{"x":[0.333,0.333],"y":[0,0]},"n":["0p667_1_0p333_0","0p667_1_0p333_0"],"t":50,"s":[100,100],"e":[0,0]},{"i":{"x":[0.667,0.667],"y":[1,1]},"o":{"x":[0.333,0.333],"y":[0,0]},"n":["0p667_1_0p333_0","0p667_1_0p333_0"],"t":59,"s":[0,0],"e":[100,100]},{"i":{"x":[0.667,0.667],"y":[1,1]},"o":{"x":[0.333,0.333],"y":[0,0]},"n":["0p667_1_0p333_0","0p667_1_0p333_0"],"t":60,"s":[100,100],"e":[100,100]},{"i":{"x":[0.667,0.667],"y":[1,1]},"o":{"x":[0.333,0.333],"y":[0,0]},"n":["0p667_1_0p333_0","0p667_1_0p333_0"],"t":80,"s":[100,100],"e":[0,0]},{"i":{"x":[0.667,0.667],"y":[1,1]},"o":{"x":[0.333,0.333],"y":[0,0]},"n":["0p667_1_0p333_0","0p667_1_0p333_0"],"t":89,"s":[0,0],"e":[100,100]},{"i":{"x":[0.667,0.667],"y":[1,1]},"o":{"x":[0.333,0.333],"y":[0,0]},"n":["0p667_1_0p333_0","0p667_1_0p333_0"],"t":90,"s":[100,100],"e":[100,100]},{"i":{"x":[0.667,0.667],"y":[1,1]},"o":{"x":[0.333,0.333],"y":[0,0]},"n":["0p667_1_0p333_0","0p667_1_0p333_0"],"t":110,"s":[100,100],"e":[0,0]},{"t":119}],"ix":3},"r":{"a":0,"k":0,"ix":6},"o":{"a":0,"k":100,"ix":7},"sk":{"a":0,"k":0,"ix":4},"sa":{"a":0,"k":0,"ix":5},"nm":"Transform"}],"nm":"Group 2","np":2,"cix":2,"ix":2,"mn":"ADBE Vector Group","hd":false},{"ty":"gr","it":[{"ind":0,"ty":"sh","ix":1,"ks":{"a":0,"k":{"i":[[25,-7.965],[-24.68,11.007]],"o":[[-32.136,10.239],[24.681,-11.009]],"v":[[-1.432,-17.008],[8.887,13.966]],"c":true},"ix":2},"nm":"Path 1","mn":"ADBE Vector Shape - Group","hd":false},{"ty":"fl","c":{"a":0,"k":[1,0.090000002992,0.6,1],"ix":4},"o":{"a":0,"k":100,"ix":5},"r":1,"nm":"Fill 1","mn":"ADBE Vector Graphic - Fill","hd":false},{"ty":"tr","p":{"a":1,"k":[{"i":{"x":0.667,"y":1},"o":{"x":0.333,"y":0},"n":"0p667_1_0p333_0","t":0,"s":[311.432,234.043],"e":[487.432,26.043],"to":[29.3333339691162,-34.6666679382324],"ti":[0,0]},{"i":{"x":0.667,"y":1},"o":{"x":0.333,"y":0},"n":"0p667_1_0p333_0","t":29,"s":[487.432,26.043],"e":[311.432,234.043],"to":[0,0],"ti":[0,0]},{"i":{"x":0.667,"y":1},"o":{"x":0.333,"y":0},"n":"0p667_1_0p333_0","t":30,"s":[311.432,234.043],"e":[487.432,26.043],"to":[0,0],"ti":[0,0]},{"i":{"x":0.667,"y":1},"o":{"x":0.333,"y":0},"n":"0p667_1_0p333_0","t":59,"s":[487.432,26.043],"e":[311.432,234.043],"to":[0,0],"ti":[0,0]},{"i":{"x":0.667,"y":1},"o":{"x":0.333,"y":0},"n":"0p667_1_0p333_0","t":60,"s":[311.432,234.043],"e":[487.432,26.043],"to":[0,0],"ti":[0,0]},{"i":{"x":0.667,"y":1},"o":{"x":0.333,"y":0},"n":"0p667_1_0p333_0","t":89,"s":[487.432,26.043],"e":[311.432,234.043],"to":[0,0],"ti":[0,0]},{"i":{"x":0.667,"y":1},"o":{"x":0.333,"y":0},"n":"0p667_1_0p333_0","t":90,"s":[311.432,234.043],"e":[487.432,26.043],"to":[0,0],"ti":[-29.3333339691162,34.6666679382324]},{"t":119}],"ix":2},"a":{"a":0,"k":[0,0],"ix":1},"s":{"a":1,"k":[{"i":{"x":[0.667,0.667],"y":[1,1]},"o":{"x":[0.333,0.333],"y":[0,0]},"n":["0p667_1_0p333_0","0p667_1_0p333_0"],"t":0,"s":[100,100],"e":[100,100]},{"i":{"x":[0.667,0.667],"y":[1,1]},"o":{"x":[0.333,0.333],"y":[0,0]},"n":["0p667_1_0p333_0","0p667_1_0p333_0"],"t":20,"s":[100,100],"e":[0,0]},{"i":{"x":[0.667,0.667],"y":[1,1]},"o":{"x":[0.333,0.333],"y":[0,0]},"n":["0p667_1_0p333_0","0p667_1_0p333_0"],"t":29,"s":[0,0],"e":[100,100]},{"i":{"x":[0.667,0.667],"y":[1,1]},"o":{"x":[0.333,0.333],"y":[0,0]},"n":["0p667_1_0p333_0","0p667_1_0p333_0"],"t":30,"s":[100,100],"e":[100,100]},{"i":{"x":[0.667,0.667],"y":[1,1]},"o":{"x":[0.333,0.333],"y":[0,0]},"n":["0p667_1_0p333_0","0p667_1_0p333_0"],"t":50,"s":[100,100],"e":[0,0]},{"i":{"x":[0.667,0.667],"y":[1,1]},"o":{"x":[0.333,0.333],"y":[0,0]},"n":["0p667_1_0p333_0","0p667_1_0p333_0"],"t":59,"s":[0,0],"e":[100,100]},{"i":{"x":[0.667,0.667],"y":[1,1]},"o":{"x":[0.333,0.333],"y":[0,0]},"n":["0p667_1_0p333_0","0p667_1_0p333_0"],"t":60,"s":[100,100],"e":[100,100]},{"i":{"x":[0.667,0.667],"y":[1,1]},"o":{"x":[0.333,0.333],"y":[0,0]},"n":["0p667_1_0p333_0","0p667_1_0p333_0"],"t":80,"s":[100,100],"e":[0,0]},{"i":{"x":[0.667,0.667],"y":[1,1]},"o":{"x":[0.333,0.333],"y":[0,0]},"n":["0p667_1_0p333_0","0p667_1_0p333_0"],"t":89,"s":[0,0],"e":[100,100]},{"i":{"x":[0.667,0.667],"y":[1,1]},"o":{"x":[0.333,0.333],"y":[0,0]},"n":["0p667_1_0p333_0","0p667_1_0p333_0"],"t":90,"s":[100,100],"e":[100,100]},{"i":{"x":[0.667,0.667],"y":[1,1]},"o":{"x":[0.333,0.333],"y":[0,0]},"n":["0p667_1_0p333_0","0p667_1_0p333_0"],"t":110,"s":[100,100],"e":[0,0]},{"t":119}],"ix":3},"r":{"a":0,"k":0,"ix":6},"o":{"a":0,"k":100,"ix":7},"sk":{"a":0,"k":0,"ix":4},"sa":{"a":0,"k":0,"ix":5},"nm":"Transform"}],"nm":"Group 3","np":2,"cix":2,"ix":3,"mn":"ADBE Vector Group","hd":false},{"ty":"gr","it":[{"ind":0,"ty":"sh","ix":1,"ks":{"a":0,"k":{"i":[[23,-5.454],[-29,6.742]],"o":[[-23,5.454],[29,-6.742]],"v":[[-7,-13.742],[1,12.454]],"c":true},"ix":2},"nm":"Path 1","mn":"ADBE Vector Shape - Group","hd":false},{"ty":"fl","c":{"a":0,"k":[0,0.788000009574,1,1],"ix":4},"o":{"a":0,"k":100,"ix":5},"r":1,"nm":"Fill 1","mn":"ADBE Vector Graphic - Fill","hd":false},{"ty":"tr","p":{"a":1,"k":[{"i":{"x":0.667,"y":1},"o":{"x":0.333,"y":0},"n":"0p667_1_0p333_0","t":0,"s":[361,298.288],"e":[501,283.288],"to":[23.3333339691162,-2.5],"ti":[0,0]},{"i":{"x":0.667,"y":1},"o":{"x":0.333,"y":0},"n":"0p667_1_0p333_0","t":29,"s":[501,283.288],"e":[361,298.288],"to":[0,0],"ti":[0,0]},{"i":{"x":0.667,"y":1},"o":{"x":0.333,"y":0},"n":"0p667_1_0p333_0","t":30,"s":[361,298.288],"e":[501,283.288],"to":[0,0],"ti":[0,0]},{"i":{"x":0.667,"y":1},"o":{"x":0.333,"y":0},"n":"0p667_1_0p333_0","t":59,"s":[501,283.288],"e":[361,298.288],"to":[0,0],"ti":[0,0]},{"i":{"x":0.667,"y":1},"o":{"x":0.333,"y":0},"n":"0p667_1_0p333_0","t":60,"s":[361,298.288],"e":[501,283.288],"to":[0,0],"ti":[0,0]},{"i":{"x":0.667,"y":1},"o":{"x":0.333,"y":0},"n":"0p667_1_0p333_0","t":89,"s":[501,283.288],"e":[361,298.288],"to":[0,0],"ti":[0,0]},{"i":{"x":0.667,"y":1},"o":{"x":0.333,"y":0},"n":"0p667_1_0p333_0","t":90,"s":[361,298.288],"e":[501,283.288],"to":[0,0],"ti":[-23.3333339691162,2.5]},{"t":119}],"ix":2},"a":{"a":0,"k":[0,0],"ix":1},"s":{"a":1,"k":[{"i":{"x":[0.667,0.667],"y":[1,1]},"o":{"x":[0.333,0.333],"y":[0,0]},"n":["0p667_1_0p333_0","0p667_1_0p333_0"],"t":0,"s":[100,100],"e":[100,100]},{"i":{"x":[0.667,0.667],"y":[1,1]},"o":{"x":[0.333,0.333],"y":[0,0]},"n":["0p667_1_0p333_0","0p667_1_0p333_0"],"t":20,"s":[100,100],"e":[0,0]},{"i":{"x":[0.667,0.667],"y":[1,1]},"o":{"x":[0.333,0.333],"y":[0,0]},"n":["0p667_1_0p333_0","0p667_1_0p333_0"],"t":29,"s":[0,0],"e":[100,100]},{"i":{"x":[0.667,0.667],"y":[1,1]},"o":{"x":[0.333,0.333],"y":[0,0]},"n":["0p667_1_0p333_0","0p667_1_0p333_0"],"t":30,"s":[100,100],"e":[100,100]},{"i":{"x":[0.667,0.667],"y":[1,1]},"o":{"x":[0.333,0.333],"y":[0,0]},"n":["0p667_1_0p333_0","0p667_1_0p333_0"],"t":50,"s":[100,100],"e":[0,0]},{"i":{"x":[0.667,0.667],"y":[1,1]},"o":{"x":[0.333,0.333],"y":[0,0]},"n":["0p667_1_0p333_0","0p667_1_0p333_0"],"t":59,"s":[0,0],"e":[100,100]},{"i":{"x":[0.667,0.667],"y":[1,1]},"o":{"x":[0.333,0.333],"y":[0,0]},"n":["0p667_1_0p333_0","0p667_1_0p333_0"],"t":60,"s":[100,100],"e":[100,100]},{"i":{"x":[0.667,0.667],"y":[1,1]},"o":{"x":[0.333,0.333],"y":[0,0]},"n":["0p667_1_0p333_0","0p667_1_0p333_0"],"t":80,"s":[100,100],"e":[0,0]},{"i":{"x":[0.667,0.667],"y":[1,1]},"o":{"x":[0.333,0.333],"y":[0,0]},"n":["0p667_1_0p333_0","0p667_1_0p333_0"],"t":89,"s":[0,0],"e":[100,100]},{"i":{"x":[0.667,0.667],"y":[1,1]},"o":{"x":[0.333,0.333],"y":[0,0]},"n":["0p667_1_0p333_0","0p667_1_0p333_0"],"t":90,"s":[100,100],"e":[100,100]},{"i":{"x":[0.667,0.667],"y":[1,1]},"o":{"x":[0.333,0.333],"y":[0,0]},"n":["0p667_1_0p333_0","0p667_1_0p333_0"],"t":110,"s":[100,100],"e":[0,0]},{"t":119}],"ix":3},"r":{"a":0,"k":0,"ix":6},"o":{"a":0,"k":100,"ix":7},"sk":{"a":0,"k":0,"ix":4},"sa":{"a":0,"k":0,"ix":5},"nm":"Transform"}],"nm":"Group 4","np":2,"cix":2,"ix":4,"mn":"ADBE Vector Group","hd":false},{"ty":"gr","it":[{"ind":0,"ty":"sh","ix":1,"ks":{"a":0,"k":{"i":[[22.752,-7],[-18.902,7.5]],"o":[[-20.028,6.162],[18.901,-7.5]],"v":[[-4.611,-13],[5.737,12.5]],"c":true},"ix":2},"nm":"Path 1","mn":"ADBE Vector Shape - Group","hd":false},{"ty":"fl","c":{"a":0,"k":[0.125,0.451000019148,0,1],"ix":4},"o":{"a":0,"k":100,"ix":5},"r":1,"nm":"Fill 1","mn":"ADBE Vector Graphic - Fill","hd":false},{"ty":"tr","p":{"a":1,"k":[{"i":{"x":0.667,"y":1},"o":{"x":0.333,"y":0},"n":"0p667_1_0p333_0","t":0,"s":[278.362,362],"e":[305.362,493],"to":[4.5,21.8333339691162],"ti":[0,0]},{"i":{"x":0.667,"y":1},"o":{"x":0.333,"y":0},"n":"0p667_1_0p333_0","t":29,"s":[305.362,493],"e":[278.362,362],"to":[0,0],"ti":[0,0]},{"i":{"x":0.667,"y":1},"o":{"x":0.333,"y":0},"n":"0p667_1_0p333_0","t":30,"s":[278.362,362],"e":[305.362,493],"to":[0,0],"ti":[0,0]},{"i":{"x":0.667,"y":1},"o":{"x":0.333,"y":0},"n":"0p667_1_0p333_0","t":59,"s":[305.362,493],"e":[278.362,362],"to":[0,0],"ti":[0,0]},{"i":{"x":0.667,"y":1},"o":{"x":0.333,"y":0},"n":"0p667_1_0p333_0","t":60,"s":[278.362,362],"e":[305.362,493],"to":[0,0],"ti":[0,0]},{"i":{"x":0.667,"y":1},"o":{"x":0.333,"y":0},"n":"0p667_1_0p333_0","t":89,"s":[305.362,493],"e":[278.362,362],"to":[0,0],"ti":[0,0]},{"i":{"x":0.667,"y":1},"o":{"x":0.333,"y":0},"n":"0p667_1_0p333_0","t":90,"s":[278.362,362],"e":[305.362,493],"to":[0,0],"ti":[-4.5,-21.8333339691162]},{"t":119}],"ix":2},"a":{"a":0,"k":[0,0],"ix":1},"s":{"a":1,"k":[{"i":{"x":[0.667,0.667],"y":[1,1]},"o":{"x":[0.333,0.333],"y":[0,0]},"n":["0p667_1_0p333_0","0p667_1_0p333_0"],"t":0,"s":[100,100],"e":[100,100]},{"i":{"x":[0.667,0.667],"y":[1,1]},"o":{"x":[0.333,0.333],"y":[0,0]},"n":["0p667_1_0p333_0","0p667_1_0p333_0"],"t":20,"s":[100,100],"e":[0,0]},{"i":{"x":[0.667,0.667],"y":[1,1]},"o":{"x":[0.333,0.333],"y":[0,0]},"n":["0p667_1_0p333_0","0p667_1_0p333_0"],"t":29,"s":[0,0],"e":[100,100]},{"i":{"x":[0.667,0.667],"y":[1,1]},"o":{"x":[0.333,0.333],"y":[0,0]},"n":["0p667_1_0p333_0","0p667_1_0p333_0"],"t":30,"s":[100,100],"e":[100,100]},{"i":{"x":[0.667,0.667],"y":[1,1]},"o":{"x":[0.333,0.333],"y":[0,0]},"n":["0p667_1_0p333_0","0p667_1_0p333_0"],"t":50,"s":[100,100],"e":[0,0]},{"i":{"x":[0.667,0.667],"y":[1,1]},"o":{"x":[0.333,0.333],"y":[0,0]},"n":["0p667_1_0p333_0","0p667_1_0p333_0"],"t":59,"s":[0,0],"e":[100,100]},{"i":{"x":[0.667,0.667],"y":[1,1]},"o":{"x":[0.333,0.333],"y":[0,0]},"n":["0p667_1_0p333_0","0p667_1_0p333_0"],"t":60,"s":[100,100],"e":[100,100]},{"i":{"x":[0.667,0.667],"y":[1,1]},"o":{"x":[0.333,0.333],"y":[0,0]},"n":["0p667_1_0p333_0","0p667_1_0p333_0"],"t":80,"s":[100,100],"e":[0,0]},{"i":{"x":[0.667,0.667],"y":[1,1]},"o":{"x":[0.333,0.333],"y":[0,0]},"n":["0p667_1_0p333_0","0p667_1_0p333_0"],"t":89,"s":[0,0],"e":[100,100]},{"i":{"x":[0.667,0.667],"y":[1,1]},"o":{"x":[0.333,0.333],"y":[0,0]},"n":["0p667_1_0p333_0","0p667_1_0p333_0"],"t":90,"s":[100,100],"e":[100,100]},{"i":{"x":[0.667,0.667],"y":[1,1]},"o":{"x":[0.333,0.333],"y":[0,0]},"n":["0p667_1_0p333_0","0p667_1_0p333_0"],"t":110,"s":[100,100],"e":[0,0]},{"t":119}],"ix":3},"r":{"a":0,"k":0,"ix":6},"o":{"a":0,"k":100,"ix":7},"sk":{"a":0,"k":0,"ix":4},"sa":{"a":0,"k":0,"ix":5},"nm":"Transform"}],"nm":"Group 5","np":2,"cix":2,"ix":5,"mn":"ADBE Vector Group","hd":false},{"ty":"gr","it":[{"ind":0,"ty":"sh","ix":1,"ks":{"a":0,"k":{"i":[[22,0],[-26.905,0]],"o":[[-22,0],[26.905,0]],"v":[[4.905,-19.5],[0,19.5]],"c":true},"ix":2},"nm":"Path 1","mn":"ADBE Vector Shape - Group","hd":false},{"ty":"fl","c":{"a":0,"k":[0,0.477999997606,1,1],"ix":4},"o":{"a":0,"k":100,"ix":5},"r":1,"nm":"Fill 1","mn":"ADBE Vector Graphic - Fill","hd":false},{"ty":"tr","p":{"a":1,"k":[{"i":{"x":0.667,"y":1},"o":{"x":0.333,"y":0},"n":"0p667_1_0p333_0","t":0,"s":[182.095,358.5],"e":[86.095,497.5],"to":[-16,23.1666660308838],"ti":[0,0]},{"i":{"x":0.667,"y":1},"o":{"x":0.333,"y":0},"n":"0p667_1_0p333_0","t":29,"s":[86.095,497.5],"e":[182.095,358.5],"to":[0,0],"ti":[0,0]},{"i":{"x":0.667,"y":1},"o":{"x":0.333,"y":0},"n":"0p667_1_0p333_0","t":30,"s":[182.095,358.5],"e":[86.095,497.5],"to":[0,0],"ti":[0,0]},{"i":{"x":0.667,"y":1},"o":{"x":0.333,"y":0},"n":"0p667_1_0p333_0","t":59,"s":[86.095,497.5],"e":[182.095,358.5],"to":[0,0],"ti":[0,0]},{"i":{"x":0.667,"y":1},"o":{"x":0.333,"y":0},"n":"0p667_1_0p333_0","t":60,"s":[182.095,358.5],"e":[86.095,497.5],"to":[0,0],"ti":[0,0]},{"i":{"x":0.667,"y":1},"o":{"x":0.333,"y":0},"n":"0p667_1_0p333_0","t":89,"s":[86.095,497.5],"e":[182.095,358.5],"to":[0,0],"ti":[0,0]},{"i":{"x":0.667,"y":1},"o":{"x":0.333,"y":0},"n":"0p667_1_0p333_0","t":90,"s":[182.095,358.5],"e":[86.095,497.5],"to":[0,0],"ti":[16,-23.1666660308838]},{"t":119}],"ix":2},"a":{"a":0,"k":[0,0],"ix":1},"s":{"a":1,"k":[{"i":{"x":[0.667,0.667],"y":[1,1]},"o":{"x":[0.333,0.333],"y":[0,0]},"n":["0p667_1_0p333_0","0p667_1_0p333_0"],"t":0,"s":[100,100],"e":[100,100]},{"i":{"x":[0.667,0.667],"y":[1,1]},"o":{"x":[0.333,0.333],"y":[0,0]},"n":["0p667_1_0p333_0","0p667_1_0p333_0"],"t":20,"s":[100,100],"e":[0,0]},{"i":{"x":[0.667,0.667],"y":[1,1]},"o":{"x":[0.333,0.333],"y":[0,0]},"n":["0p667_1_0p333_0","0p667_1_0p333_0"],"t":29,"s":[0,0],"e":[100,100]},{"i":{"x":[0.667,0.667],"y":[1,1]},"o":{"x":[0.333,0.333],"y":[0,0]},"n":["0p667_1_0p333_0","0p667_1_0p333_0"],"t":30,"s":[100,100],"e":[100,100]},{"i":{"x":[0.667,0.667],"y":[1,1]},"o":{"x":[0.333,0.333],"y":[0,0]},"n":["0p667_1_0p333_0","0p667_1_0p333_0"],"t":50,"s":[100,100],"e":[0,0]},{"i":{"x":[0.667,0.667],"y":[1,1]},"o":{"x":[0.333,0.333],"y":[0,0]},"n":["0p667_1_0p333_0","0p667_1_0p333_0"],"t":59,"s":[0,0],"e":[100,100]},{"i":{"x":[0.667,0.667],"y":[1,1]},"o":{"x":[0.333,0.333],"y":[0,0]},"n":["0p667_1_0p333_0","0p667_1_0p333_0"],"t":60,"s":[100,100],"e":[100,100]},{"i":{"x":[0.667,0.667],"y":[1,1]},"o":{"x":[0.333,0.333],"y":[0,0]},"n":["0p667_1_0p333_0","0p667_1_0p333_0"],"t":80,"s":[100,100],"e":[0,0]},{"i":{"x":[0.667,0.667],"y":[1,1]},"o":{"x":[0.333,0.333],"y":[0,0]},"n":["0p667_1_0p333_0","0p667_1_0p333_0"],"t":89,"s":[0,0],"e":[100,100]},{"i":{"x":[0.667,0.667],"y":[1,1]},"o":{"x":[0.333,0.333],"y":[0,0]},"n":["0p667_1_0p333_0","0p667_1_0p333_0"],"t":90,"s":[100,100],"e":[100,100]},{"i":{"x":[0.667,0.667],"y":[1,1]},"o":{"x":[0.333,0.333],"y":[0,0]},"n":["0p667_1_0p333_0","0p667_1_0p333_0"],"t":110,"s":[100,100],"e":[0,0]},{"t":119}],"ix":3},"r":{"a":0,"k":0,"ix":6},"o":{"a":0,"k":100,"ix":7},"sk":{"a":0,"k":0,"ix":4},"sa":{"a":0,"k":0,"ix":5},"nm":"Transform"}],"nm":"Group 6","np":2,"cix":2,"ix":6,"mn":"ADBE Vector Group","hd":false},{"ty":"gr","it":[{"ind":0,"ty":"sh","ix":1,"ks":{"a":0,"k":{"i":[[8.326,18.585],[-23,-22.881]],"o":[[-8.936,-19.947],[23,22.882]],"v":[[25,-10.734],[-10.326,7.799]],"c":true},"ix":2},"nm":"Path 1","mn":"ADBE Vector Shape - Group","hd":false},{"ty":"fl","c":{"a":0,"k":[1,0.090000002992,0.113999998803,1],"ix":4},"o":{"a":0,"k":100,"ix":5},"r":1,"nm":"Fill 1","mn":"ADBE Vector Graphic - Fill","hd":false},{"ty":"tr","p":{"a":1,"k":[{"i":{"x":0.667,"y":1},"o":{"x":0.333,"y":0},"n":"0p667_1_0p333_0","t":0,"s":[142.326,317.319],"e":[15.326,317.319],"to":[-21.1666660308838,0],"ti":[0,0]},{"i":{"x":0.667,"y":1},"o":{"x":0.333,"y":0},"n":"0p667_1_0p333_0","t":29,"s":[15.326,317.319],"e":[142.326,317.319],"to":[0,0],"ti":[0,0]},{"i":{"x":0.667,"y":1},"o":{"x":0.333,"y":0},"n":"0p667_1_0p333_0","t":30,"s":[142.326,317.319],"e":[15.326,317.319],"to":[0,0],"ti":[0,0]},{"i":{"x":0.667,"y":1},"o":{"x":0.333,"y":0},"n":"0p667_1_0p333_0","t":59,"s":[15.326,317.319],"e":[142.326,317.319],"to":[0,0],"ti":[0,0]},{"i":{"x":0.667,"y":1},"o":{"x":0.333,"y":0},"n":"0p667_1_0p333_0","t":60,"s":[142.326,317.319],"e":[15.326,317.319],"to":[0,0],"ti":[0,0]},{"i":{"x":0.667,"y":1},"o":{"x":0.333,"y":0},"n":"0p667_1_0p333_0","t":89,"s":[15.326,317.319],"e":[142.326,317.319],"to":[0,0],"ti":[0,0]},{"i":{"x":0.667,"y":1},"o":{"x":0.333,"y":0},"n":"0p667_1_0p333_0","t":90,"s":[142.326,317.319],"e":[15.326,317.319],"to":[0,0],"ti":[21.1666660308838,0]},{"t":119}],"ix":2},"a":{"a":0,"k":[0,0],"ix":1},"s":{"a":1,"k":[{"i":{"x":[0.667,0.667],"y":[1,1]},"o":{"x":[0.333,0.333],"y":[0,0]},"n":["0p667_1_0p333_0","0p667_1_0p333_0"],"t":0,"s":[100,100],"e":[100,100]},{"i":{"x":[0.667,0.667],"y":[1,1]},"o":{"x":[0.333,0.333],"y":[0,0]},"n":["0p667_1_0p333_0","0p667_1_0p333_0"],"t":20,"s":[100,100],"e":[0,0]},{"i":{"x":[0.667,0.667],"y":[1,1]},"o":{"x":[0.333,0.333],"y":[0,0]},"n":["0p667_1_0p333_0","0p667_1_0p333_0"],"t":29,"s":[0,0],"e":[100,100]},{"i":{"x":[0.667,0.667],"y":[1,1]},"o":{"x":[0.333,0.333],"y":[0,0]},"n":["0p667_1_0p333_0","0p667_1_0p333_0"],"t":30,"s":[100,100],"e":[100,100]},{"i":{"x":[0.667,0.667],"y":[1,1]},"o":{"x":[0.333,0.333],"y":[0,0]},"n":["0p667_1_0p333_0","0p667_1_0p333_0"],"t":50,"s":[100,100],"e":[0,0]},{"i":{"x":[0.667,0.667],"y":[1,1]},"o":{"x":[0.333,0.333],"y":[0,0]},"n":["0p667_1_0p333_0","0p667_1_0p333_0"],"t":59,"s":[0,0],"e":[100,100]},{"i":{"x":[0.667,0.667],"y":[1,1]},"o":{"x":[0.333,0.333],"y":[0,0]},"n":["0p667_1_0p333_0","0p667_1_0p333_0"],"t":60,"s":[100,100],"e":[100,100]},{"i":{"x":[0.667,0.667],"y":[1,1]},"o":{"x":[0.333,0.333],"y":[0,0]},"n":["0p667_1_0p333_0","0p667_1_0p333_0"],"t":80,"s":[100,100],"e":[0,0]},{"i":{"x":[0.667,0.667],"y":[1,1]},"o":{"x":[0.333,0.333],"y":[0,0]},"n":["0p667_1_0p333_0","0p667_1_0p333_0"],"t":89,"s":[0,0],"e":[100,100]},{"i":{"x":[0.667,0.667],"y":[1,1]},"o":{"x":[0.333,0.333],"y":[0,0]},"n":["0p667_1_0p333_0","0p667_1_0p333_0"],"t":90,"s":[100,100],"e":[100,100]},{"i":{"x":[0.667,0.667],"y":[1,1]},"o":{"x":[0.333,0.333],"y":[0,0]},"n":["0p667_1_0p333_0","0p667_1_0p333_0"],"t":110,"s":[100,100],"e":[0,0]},{"t":119}],"ix":3},"r":{"a":0,"k":0,"ix":6},"o":{"a":0,"k":100,"ix":7},"sk":{"a":0,"k":0,"ix":4},"sa":{"a":0,"k":0,"ix":5},"nm":"Transform"}],"nm":"Group 7","np":2,"cix":2,"ix":7,"mn":"ADBE Vector Group","hd":false},{"ty":"gr","it":[{"ind":0,"ty":"sh","ix":1,"ks":{"a":0,"k":{"i":[[29,-7.504],[-20,6]],"o":[[-17.191,4.448],[20,-6]],"v":[[-6.404,-10],[3.596,11.504]],"c":true},"ix":2},"nm":"Path 1","mn":"ADBE Vector Shape - Group","hd":false},{"ty":"fl","c":{"a":0,"k":[0,0.477999997606,0.713999968884,1],"ix":4},"o":{"a":0,"k":100,"ix":5},"r":1,"nm":"Fill 1","mn":"ADBE Vector Graphic - Fill","hd":false},{"ty":"tr","p":{"a":1,"k":[{"i":{"x":0.667,"y":1},"o":{"x":0.333,"y":0},"n":"0p667_1_0p333_0","t":0,"s":[173.763,263.708],"e":[14.763,150.708],"to":[-26.5,-18.8333339691162],"ti":[5.23961639404297,-8.93524646759033]},{"i":{"x":0.667,"y":1},"o":{"x":0.333,"y":0},"n":"0p667_1_0p333_0","t":29,"s":[14.763,150.708],"e":[142.326,317.319],"to":[-5.23961639404297,8.93524646759033],"ti":[-0.09371694177389,-27.7685794830322]},{"i":{"x":0.667,"y":1},"o":{"x":0.333,"y":0},"n":"0p667_1_0p333_0","t":30,"s":[142.326,317.319],"e":[15.326,317.319],"to":[0.09371694177389,27.7685794830322],"ti":[0,0]},{"i":{"x":0.667,"y":1},"o":{"x":0.333,"y":0},"n":"0p667_1_0p333_0","t":59,"s":[15.326,317.319],"e":[142.326,317.319],"to":[0,0],"ti":[0,0]},{"i":{"x":0.667,"y":1},"o":{"x":0.333,"y":0},"n":"0p667_1_0p333_0","t":60,"s":[142.326,317.319],"e":[15.326,317.319],"to":[0,0],"ti":[0,0]},{"i":{"x":0.667,"y":1},"o":{"x":0.333,"y":0},"n":"0p667_1_0p333_0","t":89,"s":[15.326,317.319],"e":[142.326,317.319],"to":[0,0],"ti":[0,0]},{"i":{"x":0.667,"y":1},"o":{"x":0.333,"y":0},"n":"0p667_1_0p333_0","t":90,"s":[142.326,317.319],"e":[15.326,317.319],"to":[0,0],"ti":[21.1666660308838,0]},{"t":119}],"ix":2},"a":{"a":0,"k":[0,0],"ix":1},"s":{"a":1,"k":[{"i":{"x":[0.667,0.667],"y":[1,1]},"o":{"x":[0.333,0.333],"y":[0,0]},"n":["0p667_1_0p333_0","0p667_1_0p333_0"],"t":0,"s":[100,100],"e":[100,100]},{"i":{"x":[0.667,0.667],"y":[1,1]},"o":{"x":[0.333,0.333],"y":[0,0]},"n":["0p667_1_0p333_0","0p667_1_0p333_0"],"t":20,"s":[100,100],"e":[0,0]},{"i":{"x":[0.667,0.667],"y":[1,1]},"o":{"x":[0.333,0.333],"y":[0,0]},"n":["0p667_1_0p333_0","0p667_1_0p333_0"],"t":29,"s":[0,0],"e":[100,100]},{"i":{"x":[0.667,0.667],"y":[1,1]},"o":{"x":[0.333,0.333],"y":[0,0]},"n":["0p667_1_0p333_0","0p667_1_0p333_0"],"t":30,"s":[100,100],"e":[100,100]},{"i":{"x":[0.667,0.667],"y":[1,1]},"o":{"x":[0.333,0.333],"y":[0,0]},"n":["0p667_1_0p333_0","0p667_1_0p333_0"],"t":50,"s":[100,100],"e":[0,0]},{"i":{"x":[0.667,0.667],"y":[1,1]},"o":{"x":[0.333,0.333],"y":[0,0]},"n":["0p667_1_0p333_0","0p667_1_0p333_0"],"t":59,"s":[0,0],"e":[100,100]},{"i":{"x":[0.667,0.667],"y":[1,1]},"o":{"x":[0.333,0.333],"y":[0,0]},"n":["0p667_1_0p333_0","0p667_1_0p333_0"],"t":60,"s":[100,100],"e":[100,100]},{"i":{"x":[0.667,0.667],"y":[1,1]},"o":{"x":[0.333,0.333],"y":[0,0]},"n":["0p667_1_0p333_0","0p667_1_0p333_0"],"t":80,"s":[100,100],"e":[0,0]},{"i":{"x":[0.667,0.667],"y":[1,1]},"o":{"x":[0.333,0.333],"y":[0,0]},"n":["0p667_1_0p333_0","0p667_1_0p333_0"],"t":89,"s":[0,0],"e":[100,100]},{"i":{"x":[0.667,0.667],"y":[1,1]},"o":{"x":[0.333,0.333],"y":[0,0]},"n":["0p667_1_0p333_0","0p667_1_0p333_0"],"t":90,"s":[100,100],"e":[100,100]},{"i":{"x":[0.667,0.667],"y":[1,1]},"o":{"x":[0.333,0.333],"y":[0,0]},"n":["0p667_1_0p333_0","0p667_1_0p333_0"],"t":110,"s":[100,100],"e":[0,0]},{"t":119}],"ix":3},"r":{"a":0,"k":0,"ix":6},"o":{"a":0,"k":100,"ix":7},"sk":{"a":0,"k":0,"ix":4},"sa":{"a":0,"k":0,"ix":5},"nm":"Transform"}],"nm":"Group 8","np":2,"cix":2,"ix":8,"mn":"ADBE Vector Group","hd":false},{"ty":"gr","it":[{"ind":0,"ty":"sh","ix":1,"ks":{"a":0,"k":{"i":[[18.922,-4],[-19.709,1]],"o":[[-18.921,4],[19.708,-1]],"v":[[-3.079,-10.5],[2.292,13.5]],"c":true},"ix":2},"nm":"Path 1","mn":"ADBE Vector Shape - Group","hd":false},{"ty":"fl","c":{"a":0,"k":[0,0.477999997606,1,1],"ix":4},"o":{"a":0,"k":100,"ix":5},"r":1,"nm":"Fill 1","mn":"ADBE Vector Graphic - Fill","hd":false},{"ty":"tr","p":{"a":1,"k":[{"i":{"x":0.667,"y":1},"o":{"x":0.333,"y":0},"n":"0p667_1_0p333_0","t":0,"s":[206.049,226.465],"e":[45.049,18.465],"to":[-26.8333339691162,-34.6666679382324],"ti":[0,0]},{"i":{"x":0.667,"y":1},"o":{"x":0.333,"y":0},"n":"0p667_1_0p333_0","t":29,"s":[45.049,18.465],"e":[206.049,226.465],"to":[0,0],"ti":[0,0]},{"i":{"x":0.667,"y":1},"o":{"x":0.333,"y":0},"n":"0p667_1_0p333_0","t":30,"s":[206.049,226.465],"e":[45.049,18.465],"to":[0,0],"ti":[0,0]},{"i":{"x":0.667,"y":1},"o":{"x":0.333,"y":0},"n":"0p667_1_0p333_0","t":59,"s":[45.049,18.465],"e":[206.049,226.465],"to":[0,0],"ti":[0,0]},{"i":{"x":0.667,"y":1},"o":{"x":0.333,"y":0},"n":"0p667_1_0p333_0","t":60,"s":[206.049,226.465],"e":[45.049,18.465],"to":[0,0],"ti":[0,0]},{"i":{"x":0.667,"y":1},"o":{"x":0.333,"y":0},"n":"0p667_1_0p333_0","t":89,"s":[45.049,18.465],"e":[206.049,226.465],"to":[0,0],"ti":[0,0]},{"i":{"x":0.667,"y":1},"o":{"x":0.333,"y":0},"n":"0p667_1_0p333_0","t":90,"s":[206.049,226.465],"e":[45.049,18.465],"to":[0,0],"ti":[26.8333339691162,34.6666679382324]},{"t":119}],"ix":2},"a":{"a":0,"k":[0,0],"ix":1},"s":{"a":1,"k":[{"i":{"x":[0.667,0.667],"y":[1,1]},"o":{"x":[0.333,0.333],"y":[0,0]},"n":["0p667_1_0p333_0","0p667_1_0p333_0"],"t":0,"s":[100,100],"e":[100,100]},{"i":{"x":[0.667,0.667],"y":[1,1]},"o":{"x":[0.333,0.333],"y":[0,0]},"n":["0p667_1_0p333_0","0p667_1_0p333_0"],"t":20,"s":[100,100],"e":[0,0]},{"i":{"x":[0.667,0.667],"y":[1,1]},"o":{"x":[0.333,0.333],"y":[0,0]},"n":["0p667_1_0p333_0","0p667_1_0p333_0"],"t":29,"s":[0,0],"e":[100,100]},{"i":{"x":[0.667,0.667],"y":[1,1]},"o":{"x":[0.333,0.333],"y":[0,0]},"n":["0p667_1_0p333_0","0p667_1_0p333_0"],"t":30,"s":[100,100],"e":[100,100]},{"i":{"x":[0.667,0.667],"y":[1,1]},"o":{"x":[0.333,0.333],"y":[0,0]},"n":["0p667_1_0p333_0","0p667_1_0p333_0"],"t":50,"s":[100,100],"e":[0,0]},{"i":{"x":[0.667,0.667],"y":[1,1]},"o":{"x":[0.333,0.333],"y":[0,0]},"n":["0p667_1_0p333_0","0p667_1_0p333_0"],"t":59,"s":[0,0],"e":[100,100]},{"i":{"x":[0.667,0.667],"y":[1,1]},"o":{"x":[0.333,0.333],"y":[0,0]},"n":["0p667_1_0p333_0","0p667_1_0p333_0"],"t":60,"s":[100,100],"e":[100,100]},{"i":{"x":[0.667,0.667],"y":[1,1]},"o":{"x":[0.333,0.333],"y":[0,0]},"n":["0p667_1_0p333_0","0p667_1_0p333_0"],"t":80,"s":[100,100],"e":[0,0]},{"i":{"x":[0.667,0.667],"y":[1,1]},"o":{"x":[0.333,0.333],"y":[0,0]},"n":["0p667_1_0p333_0","0p667_1_0p333_0"],"t":89,"s":[0,0],"e":[100,100]},{"i":{"x":[0.667,0.667],"y":[1,1]},"o":{"x":[0.333,0.333],"y":[0,0]},"n":["0p667_1_0p333_0","0p667_1_0p333_0"],"t":90,"s":[100,100],"e":[100,100]},{"i":{"x":[0.667,0.667],"y":[1,1]},"o":{"x":[0.333,0.333],"y":[0,0]},"n":["0p667_1_0p333_0","0p667_1_0p333_0"],"t":110,"s":[100,100],"e":[0,0]},{"t":119}],"ix":3},"r":{"a":0,"k":0,"ix":6},"o":{"a":0,"k":100,"ix":7},"sk":{"a":0,"k":0,"ix":4},"sa":{"a":0,"k":0,"ix":5},"nm":"Transform"}],"nm":"Group 9","np":2,"cix":2,"ix":9,"mn":"ADBE Vector Group","hd":false},{"ty":"tr","p":{"a":0,"k":[248.645,248.819],"ix":2},"a":{"a":0,"k":[248.645,248.819],"ix":1},"s":{"a":0,"k":[100,100],"ix":3},"r":{"a":0,"k":0,"ix":6},"o":{"a":0,"k":100,"ix":7},"sk":{"a":0,"k":0,"ix":4},"sa":{"a":0,"k":0,"ix":5},"nm":"Transform"}],"nm":"particles","np":9,"cix":2,"ix":2,"mn":"ADBE Vector Group","hd":false},{"ty":"gr","it":[{"ind":0,"ty":"sh","ix":1,"ks":{"a":0,"k":{"i":[[0,11.041],[-11.04,0],[0,-11.041],[11.041,0]],"o":[[0,-11.041],[11.041,0],[0,11.041],[-11.04,0]],"v":[[-19.991,0],[0,-19.991],[19.991,0],[0,19.991]],"c":true},"ix":2},"nm":"Path 1","mn":"ADBE Vector Shape - Group","hd":false},{"ty":"fl","c":{"a":0,"k":[0,0,0,1],"ix":4},"o":{"a":1,"k":[{"i":{"x":[0.833],"y":[0.833]},"o":{"x":[0.167],"y":[0.167]},"n":["0p833_0p833_0p167_0p167"],"t":0,"s":[100],"e":[0]},{"i":{"x":[0.833],"y":[0.833]},"o":{"x":[0.167],"y":[0.167]},"n":["0p833_0p833_0p167_0p167"],"t":59,"s":[0],"e":[100]},{"i":{"x":[0.833],"y":[0.833]},"o":{"x":[0.167],"y":[0.167]},"n":["0p833_0p833_0p167_0p167"],"t":60,"s":[100],"e":[0]},{"t":119}],"ix":5},"r":1,"nm":"Fill 1","mn":"ADBE Vector Graphic - Fill","hd":false},{"ty":"tr","p":{"a":0,"k":[256,256],"ix":2},"a":{"a":0,"k":[0,0],"ix":1},"s":{"a":1,"k":[{"i":{"x":[0.667,0.667],"y":[1,1]},"o":{"x":[0.333,0.333],"y":[0,0]},"n":["0p667_1_0p333_0","0p667_1_0p333_0"],"t":0,"s":[100,100],"e":[1152,1152]},{"i":{"x":[0.667,0.667],"y":[1,1]},"o":{"x":[0.167,0.167],"y":[0,0]},"n":["0p667_1_0p167_0","0p667_1_0p167_0"],"t":59,"s":[1152,1152],"e":[100,100]},{"i":{"x":[0.667,0.667],"y":[1,1]},"o":{"x":[0.333,0.333],"y":[0,0]},"n":["0p667_1_0p333_0","0p667_1_0p333_0"],"t":60,"s":[100,100],"e":[1152,1152]},{"t":119}],"ix":3},"r":{"a":0,"k":0,"ix":6},"o":{"a":0,"k":100,"ix":7},"sk":{"a":0,"k":0,"ix":4},"sa":{"a":0,"k":0,"ix":5},"nm":"Transform"}],"nm":"Group 40","np":2,"cix":2,"ix":3,"mn":"ADBE Vector Group","hd":false}],"ip":0,"op":120,"st":0,"bm":0}],"markers":[]}